{
    "<page title>": "60A4RAT1EU, S604EA3, Lenovo, LCD Monitor, Itenergy Ltd",
    "adjustable display angle": "Yes",
    "adjustable display height": "Yes",
    "adjustable display pivot": "Yes",
    "aspect ratio": "16:10",
    "backlight technology": "LED",
    "brand name": "Lenovo",
    "brightness": "300 cd/m\u00c2\u00b2",
    "builtin devices": "USB Hub",
    "certifications  standards": "CTUVusCSACB ReportNEMKONOMSASOTUV-GSCCCGOSTPSBBSMIKCJEIDATUV-SISCKVALITETKUCASINSMSABSSTZBELLISOTANKONCARCSMSONCAPEMIFCC BICCEVCCIKCC-TickSABSBSMICCCERGONOMICVOCCECPe-Standby",
    "colour": "Business Black",
    "colour support": "1.07 Billion Colors",
    "contrast ratio": "1,000:1",
    "depth": "62 mm",
    "depth with stand": "241.81 mm",
    "displayport": "Yes",
    "dvi": "Yes",
    "features": [
        "Picture in Picture",
        "Digital Daisy Chain",
        "Picture by Picture",
        "Security Lock",
        "Mobile High-Definition Link (MHL)"
    ],
    "full datasheet accessories features": ".sep { font-family: Arial, Helvetica, sans-serif; font-size: 8pt; color: #b0b0b0; background-color: #b0b0b0; margin-bottom: 20pt; }\n.spec { font-family: Arial, Helvetica, sans-serif; margin-bottom: 5pt; font-size: 8pt; }\n.sect { font-family: Arial, Helvetica, sans-serif; font-size: 8pt; font-weight: bold; }\n.para { font-family: Arial, Helvetica, sans-serif; font-weight: bold; font-siez: 10pt; background-color: #b0b0b0; color: black; }\n.descr { font-family: Arial, Helvetica, sans-serif; font-size: 10pt; }\nDetails\nGeneral Information\nManufacturer\nLenovo Group Limited\nManufacturer Part Number\n60A4RAT1EU\nBrand Name\nLenovo\nProduct Line\nThinkVision\nProduct Model\nLT3053p\nProduct Name\nThinkVision LT3053p 30-inch WQXGA IPS LED Backlit LCD Professional Monitor\nPackaged Quantity\n1\nProduct Type\nLCD Monitor\nTechnical Information\nNumber of Screens\n1\nScreen Size\n76.2 cm (30\")\nScreen Mode\nWQXGA\nPanel Technology\nAdvanced High Performance In-plane Switching (AH-IPS) Technology\nResponse Time\n6 ms\nAspect Ratio\n16:10\nHorizontal Viewing Angle\n178\u00c2\u00b0\nVertical Viewing Angle\n178\u00c2\u00b0\nAdjustable Display Angle\nYes\nAdjustable Display Height\nYes\nAdjustable Display Pivot\nYes\nBacklight Technology\nLED\nFeatures\nSecurity Lock\nFeatures\nMobile High-Definition Link (MHL)\nFeatures\nPicture by Picture\nFeatures\nPicture in Picture\nFeatures\nDigital Daisy Chain\nVideo\nMaximum Resolution\n2560 x 1600\nStandard Refresh Rate\n60 Hz\nColour Support\n1.07 Billion Colors\nContrast Ratio\n1,000:1\nBrightness\n300 cd/m\u00c2\u00b2\nInterfaces/Ports\nDVI\nYes\nHDMI\nYes\nUSB\nYes\nUSB Standard\nUSB 3.0\nVGA\nYes\nDisplayPort\nYes\nBuilt-in Devices\nBuilt-in Devices\nUSB Hub\nPower Description\nInput Voltage\n110 V AC\nInput Voltage\n220 V AC\nOperating Power Consumption\n130 W\nStandby Power Consumption\n1.20 W\nOff-Mode Power Consumption\n500 mW\nPhysical Characteristics\nVESA Mount Compatible\nYes\nVESA Mount Standard\n100 x 100\nColour\nBusiness Black\nWidth\n690.1 mm\nDepth\n62 mm\nHeight with Stand\n471.17 mm\nWidth with Stand\n690.12 mm\nDepth with Stand\n241.81 mm\nWeight (Approximate)\n11.50 kg\nMiscellaneous\nCertifications & Standards\nCTUVusCSACB ReportNEMKONOMSASOTUV-GSCCCGOSTPSBBSMIKCJEIDATUV-SISCKVALITETKUCASINSMSABSSTZBELLISOTANKONCARCSMSONCAPEMIFCC BICCEVCCIKCC-TickSABSBSMICCCERGONOMICVOCCECPe-Standby\nPlatform Supported\nPC\nGreen Compliant\nYes\nGreen Compliance Certificate/Authority\nEPEAT Gold\nGreen Compliance Certificate/Authority\nENERGY STAR 6.0\nGreen Compliance Certificate/Authority\nTCO Certified Displays 6.0\nGreen Compliance Certificate/Authority\nULE Gold\nGreen Compliance Certificate/Authority\nChina RoHS\nGreen Compliance Certificate/Authority\nChina Energy Label (CEL)\nGreen Compliance Certificate/Authority\nCECP\nGreen Compliance Certificate/Authority\nEPA\nGreen Compliance Certificate/Authority\nTaiwan Green Mark\nGreen Compliance Certificate/Authority\nTCO Certified Edge\nGreen Compliance Certificate/Authority\nREACH\nGreen Compliance Certificate/Authority\nTurkey RoHS\nNo accessories available\nProduct feature could not be found.",
    "green compliance certificateauthority": [
        "China RoHS",
        "CECP",
        "REACH",
        "TCO Certified Displays 6.0",
        "Taiwan Green Mark",
        "China Energy Label (CEL)",
        "ULE Gold",
        "TCO Certified Edge",
        "Turkey RoHS",
        "EPA",
        "ENERGY STAR 6.0",
        "EPEAT Gold"
    ],
    "green compliant": "Yes",
    "hdmi": "Yes",
    "height with stand": "471.17 mm",
    "horizontal viewing angle": "178\u00c2\u00b0",
    "input voltage": [
        "220 V AC",
        "110 V AC"
    ],
    "manufacturer": "Lenovo Group Limited",
    "manufacturer part number": "60A4RAT1EU",
    "maximum resolution": "2560 x 1600",
    "mfr code": "60A4RAT1EU",
    "number of screens": "1",
    "offmode power consumption": "500 mW",
    "operating power consumption": "130 W",
    "packaged quantity": "1",
    "panel technology": "Advanced High Performance In-plane Switching (AH-IPS) Technology",
    "platform supported": "PC",
    "product": "Lenovo ThinkVision LT3053p 76.2 cm\n(30\") LED LCD Monitor - 16:10 - 6\nms - Adjustable Display Angle -\n2560 x 1600 - 1.07 Billion Colors -\n300 cd/m\u00c3\u00af\u00c2\u00bf\u00c2\u00bd - 1,000:1 - WQXGA - DVI\n- HDMI - VGA - DisplayPort - USB -\n130 W - Business Black - EPEAT\nGold, ENERGY STAR",
    "product code": "S604EA3",
    "product line": "ThinkVision",
    "product model": "LT3053p",
    "product name": "ThinkVision LT3053p 30-inch WQXGA IPS LED Backlit LCD Professional Monitor",
    "product type": "LCD Monitor",
    "response time": "6 ms",
    "screen mode": "WQXGA",
    "screen size": "76.2 cm (30\")",
    "standard refresh rate": "60 Hz",
    "standby power consumption": "1.20 W",
    "stock": "1 - Available",
    "usb": "Yes",
    "usb standard": "USB 3.0",
    "vertical viewing angle": "178\u00c2\u00b0",
    "vesa mount compatible": "Yes",
    "vesa mount standard": "100 x 100",
    "vga": "Yes",
    "weight approximate": "11.50 kg",
    "width": "690.1 mm",
    "width with stand": "690.12 mm"
}