{
    "<page title>": "VA2046A-LED, B921483, ViewSonic, LCD Monitor, Itenergy Ltd",
    "adjustable display angle": "Yes",
    "aspect ratio": "16:9",
    "backlight technology": "LED",
    "brand name": "Viewsonic",
    "brightness": "200 cd/m\u00c2\u00b2",
    "certifications  standards": "CB UL cUL FCC-B TUV-S NOM CE GOST-R+Hygienic SASO Ukraine CCC BSMI PSB C-TICK",
    "colour": "Black",
    "colour support": "16.2 Million Colours",
    "contrast ratio": "600:1",
    "depth": "49 mm",
    "depth with stand": "197.60 mm",
    "dvi": "No",
    "features": [
        "Security Lock",
        "Eco Mode"
    ],
    "full datasheet accessories features": ".sep { font-family: Arial, Helvetica, sans-serif; font-size: 8pt; color: #b0b0b0; background-color: #b0b0b0; margin-bottom: 20pt; }\n.spec { font-family: Arial, Helvetica, sans-serif; margin-bottom: 5pt; font-size: 8pt; }\n.sect { font-family: Arial, Helvetica, sans-serif; font-size: 8pt; font-weight: bold; }\n.para { font-family: Arial, Helvetica, sans-serif; font-weight: bold; font-siez: 10pt; background-color: #b0b0b0; color: black; }\n.descr { font-family: Arial, Helvetica, sans-serif; font-size: 10pt; }\nDetails\nGeneral Information\nManufacturer\nViewsonic Corporation\nManufacturer Part Number\nVA2046A-LED\nBrand Name\nViewsonic\nProduct Model\nVA2046a-LED\nProduct Name\n20'' LED Display\nProduct Type\nLCD Monitor\nTechnical Information\nNumber of Screens\n1\nScreen Size\n50.8 cm (20\")\nScreen Mode\nHD+\nScreen Surface\nAnti-glare\nResponse Time\n5 ms\nAspect Ratio\n16:9\nHorizontal Viewing Angle\n90\u00c2\u00b0\nVertical Viewing Angle\n65\u00c2\u00b0\nAdjustable Display Angle\nYes\nMount Type\nWall Mountable\nBacklight Technology\nLED\nHDCP Supported\nNo\nFeatures\nEco Mode\nFeatures\nSecurity Lock\nVideo\nMaximum Resolution\n1600 x 900\nStandard Refresh Rate\n75 Hz\nColour Support\n16.2 Million Colours\nContrast Ratio\n600:1\nBrightness\n200 cd/m\u00c2\u00b2\nAudio\nSpeakers\nNo\nInterfaces/Ports\nDVI\nNo\nHDMI\nNo\nUSB\nNo\nVGA\nYes\nPower Description\nInput Voltage\n110 V AC\nInput Voltage\n220 V AC\nOperating Power Consumption\n18 W\nPhysical Characteristics\nVESA Mount Compatible\nYes\nVESA Mount Standard\n100 x 100\nColour\nBlack\nHeight\n301.8 mm\nWidth\n478.2 mm\nDepth\n49 mm\nHeight with Stand\n360.20 mm\nWidth with Stand\n478.20 mm\nDepth with Stand\n197.60 mm\nWeight (Approximate)\n2.60 kg\nWeight with Stand (Approximate)\n3 kg\nMiscellaneous\nPackage Contents\n20'' LED Display 1 x Power Cable 1 x D-Sub Cable 1 x Quick Start Guide 1 x CD-ROM\nCertifications & Standards\nCB UL cUL FCC-B TUV-S NOM CE GOST-R+Hygienic SASO Ukraine CCC BSMI PSB C-TICK\nPlatform Supported\nPC\nPlatform Supported\nMac\nGreen Compliant\nYes\nGreen Compliance Certificate/Authority\nWEEE\nGreen Compliance Certificate/Authority\nRoHS\nGreen Compliance Certificate/Authority\nChina Energy Label (CEL)\nWarranty\nLimited Warranty\n2 Year\nNo accessories available\nProduct feature could not be found.",
    "green compliance certificateauthority": [
        "WEEE",
        "China Energy Label (CEL)",
        "RoHS"
    ],
    "green compliant": "Yes",
    "hdcp supported": "No",
    "hdmi": "No",
    "height": "301.8 mm",
    "height with stand": "360.20 mm",
    "horizontal viewing angle": "90\u00c2\u00b0",
    "input voltage": [
        "220 V AC",
        "110 V AC"
    ],
    "limited warranty": "2 Year",
    "manufacturer": "Viewsonic Corporation",
    "manufacturer part number": "VA2046A-LED",
    "maximum resolution": "1600 x 900",
    "mfr code": "VA2046A-LED",
    "mount type": "Wall Mountable",
    "number of screens": "1",
    "operating power consumption": "18 W",
    "package contents": "20'' LED Display 1 x Power Cable 1 x D-Sub Cable 1 x Quick Start Guide 1 x CD-ROM",
    "platform supported": [
        "PC",
        "Mac"
    ],
    "product": "Viewsonic VA2046a-LED 50.8 cm (20\")\nLED LCD Monitor - 16:9 - 5 ms -\nAdjustable Display Angle - 1600 x\n900 - 16.2 Million Colours - 200\ncd/m\u00c3\u00af\u00c2\u00bf\u00c2\u00bd - 600:1 - HD+ - VGA - 18 W\n- Black - WEEE, RoHS, China Energy\nLabel (CEL)",
    "product code": "B921483",
    "product model": "VA2046a-LED",
    "product name": "20'' LED Display",
    "product type": "LCD Monitor",
    "response time": "5 ms",
    "screen mode": "HD+",
    "screen size": "50.8 cm (20\")",
    "screen surface": "Anti-glare",
    "speakers": "No",
    "standard refresh rate": "75 Hz",
    "stock": "660 - Available",
    "usb": "No",
    "vertical viewing angle": "65\u00c2\u00b0",
    "vesa mount compatible": "Yes",
    "vesa mount standard": "100 x 100",
    "vga": "Yes",
    "weight approximate": "2.60 kg",
    "weight with stand approximate": "3 kg",
    "width": "478.2 mm",
    "width with stand": "478.20 mm"
}