{
    "<page title>": "60A9MAR2UK, S603PX5, Lenovo, LCD Monitor, Itenergy Ltd",
    "adjustable display angle": "Yes",
    "adjustable display height": "Yes",
    "adjustable display pivot": "Yes",
    "aspect ratio": "16:9",
    "backlight technology": "LED",
    "brand name": "Lenovo",
    "brightness": "250 cd/m\u00c2\u00b2",
    "builtin devices": [
        "Microphone",
        "Speaker",
        "USB Hub"
    ],
    "certifications  standards": "SAFETY CU (Belarus/Russia/Uzbekistan) BSMI CCC (China) CE (Europe) CSA /cUl (Canada) CSM (Bulgaria) IEC950 CB Report INSM (Moldavia) ISC (Cambodia) JEITA KC (Korea) KEBS (Kenya) KONCAR (Croatia) KUCAS (Kuwait) KVALITET (Serbia) NOM (Mexico) OTAN (Kazakhstan) PSB (Singapore) SABS (South Africa) SASO (Saudi Arabia) SEMKO or NEMKO SONCAP (Nigeria) Tanzania TUV -GS (Germany) TUV-S or IRAM-S (Argentina) Ukraine UL or c(TUV)us (USA) EMI BSMI (Taiwan) CCC (China) CE (Europe) CSM (Bulgaria) C-tick (Australia/New Zealand) FCC B (USA) IC (Canada) KC (Korea) KONCAR (Croatia) KVALITET (Serbia) SABS-CoC, LoA (South Africa) SASO (Saudi Arabia) VCCI (Japan) ERGONOMIC E-standby (Korea) CECP (China) CEL (China) Tier 1 Environmentally Responsible Certifications Carbon footprint ULE Gold VOC (US)",
    "colour": "Raven Black",
    "colour support": "16.7 Million Colours",
    "contrast ratio": "2,000,000:1",
    "depth": "12.7 mm",
    "display orientation": "Landscape/Portrait",
    "dvi": "Yes",
    "features": [
        "VoIP Controls",
        "Zero Power Switch",
        "Mobile High-Definition Link (MHL)"
    ],
    "full datasheet accessories features": ".sep { font-family: Arial, Helvetica, sans-serif; font-size: 8pt; color: #b0b0b0; background-color: #b0b0b0; margin-bottom: 20pt; }\n.spec { font-family: Arial, Helvetica, sans-serif; margin-bottom: 5pt; font-size: 8pt; }\n.sect { font-family: Arial, Helvetica, sans-serif; font-size: 8pt; font-weight: bold; }\n.para { font-family: Arial, Helvetica, sans-serif; font-weight: bold; font-siez: 10pt; background-color: #b0b0b0; color: black; }\n.descr { font-family: Arial, Helvetica, sans-serif; font-size: 10pt; }\nDetails\nGeneral Information\nManufacturer\nLenovo Group Limited\nManufacturer Part Number\n60A9MAR2UK\nBrand Name\nLenovo\nProduct Line\nThinkVision\nProduct Model\nLT2223d\nProduct Name\nThinkVision LT2223d 21.5-inch FHD LED Backlit LCD OneLink Docking Monitor\nProduct Type\nLCD Monitor\nTechnical Information\nNumber of Screens\n1\nScreen Size\n54.6 cm (21.5\")\nScreen Mode\nFull HD\nScreen Surface\nAnti-glare\nPanel Technology\nTwisted Nematic Film (TN Film)\nResponse Time\n5 ms\nAspect Ratio\n16:9\nHorizontal Viewing Angle\n176\u00c2\u00b0\nVertical Viewing Angle\n170\u00c2\u00b0\nAdjustable Display Angle\nYes\nAdjustable Display Height\nYes\nAdjustable Display Pivot\nYes\nDisplay Orientation\nLandscape/Portrait\nBacklight Technology\nLED\nTilt Angle\n-5\u00c2\u00b0to30\u00c2\u00b0\nSwivel Angle\n-45\u00c2\u00b0\nFeatures\nVoIP Controls\nFeatures\nZero Power Switch\nFeatures\nMobile High-Definition Link (MHL)\nVideo\nMaximum Resolution\n1920 x 1080\nStandard Refresh Rate\n75 Hz\nColour Support\n16.7 Million Colours\nContrast Ratio\n2,000,000:1\nBrightness\n250 cd/m\u00c2\u00b2\nAudio\nNumber of Speakers\n2\nSpeakers\nYes\nInterfaces/Ports\nDVI\nYes\nHDMI\nYes\nUSB\nYes\nUSB Standard\nUSB 3.0\nVGA\nYes\nNetwork (RJ-45)\nYes\nBuilt-in Devices\nBuilt-in Devices\nMicrophone\nBuilt-in Devices\nSpeaker\nBuilt-in Devices\nUSB Hub\nWebcam\nYes\nPower Description\nInput Voltage\n110 V AC\nInput Voltage\n220 V AC\nOperating Power Consumption\n30 W\nStandby Power Consumption\n500 mW\nOff-Mode Power Consumption\n500 mW\nPhysical Characteristics\nVESA Mount Compatible\nYes\nVESA Mount Standard\n100 x 100\nColour\nRaven Black\nHeight\n226.1 mm\nWidth\n348 mm\nDepth\n12.7 mm\nWeight (Approximate)\n2.86 kg\nMiscellaneous\nPackage Contents\nThinkVision LT2223d 21.5-inch FHD LED Backlit LCD OneLink Docking Monitor Detachable tool-less full ergo stand OneLink Cable VGA Cable USB Cable 135w Power Adapter + Cord CD containing multilingual user's guide, setup test pattern, and Windows installation file Quick start and safety poster\nCertifications & Standards\nSAFETY CU (Belarus/Russia/Uzbekistan) BSMI CCC (China) CE (Europe) CSA /cUl (Canada) CSM (Bulgaria) IEC950 CB Report INSM (Moldavia) ISC (Cambodia) JEITA KC (Korea) KEBS (Kenya) KONCAR (Croatia) KUCAS (Kuwait) KVALITET (Serbia) NOM (Mexico) OTAN (Kazakhstan) PSB (Singapore) SABS (South Africa) SASO (Saudi Arabia) SEMKO or NEMKO SONCAP (Nigeria) Tanzania TUV -GS (Germany) TUV-S or IRAM-S (Argentina) Ukraine UL or c(TUV)us (USA) EMI BSMI (Taiwan) CCC (China) CE (Europe) CSM (Bulgaria) C-tick (Australia/New Zealand) FCC B (USA) IC (Canada) KC (Korea) KONCAR (Croatia) KVALITET (Serbia) SABS-CoC, LoA (South Africa) SASO (Saudi Arabia) VCCI (Japan) ERGONOMIC E-standby (Korea) CECP (China) CEL (China) Tier 1 Environmentally Responsible Certifications Carbon footprint ULE Gold VOC (US)\nGreen Compliant\nYes\nGreen Compliance Certificate/Authority\nENERGY STAR 6.0\nGreen Compliance Certificate/Authority\nULE Gold\nGreen Compliance Certificate/Authority\nEPEAT Gold\nGreen Compliance Certificate/Authority\nTCO '06\nGreen Compliance Certificate/Authority\nTCO Certified Edge Displays 1.2\nGreen Compliance Certificate/Authority\nRoHS\nGreen Compliance Certificate/Authority\nChina Energy Label (CEL)\nGreen Compliance Certificate/Authority\nWEEE\nGreen Compliance Certificate/Authority\nTurkey RoHS\nGreen Compliance Certificate/Authority\nChina RoHS\nGreen Compliance Certificate/Authority\nUkraine RoHS\nGreen Compliance Certificate/Authority\nTaiwan Green Mark\nGreen Compliance Certificate/Authority\nEU RoHS\nWarranty\nLimited Warranty\n3 Year\nNo accessories available\nProduct feature could not be found.",
    "green compliance certificateauthority": [
        "TCO Certified Edge Displays 1.2",
        "ULE Gold",
        "China Energy Label (CEL)",
        "ENERGY STAR 6.0",
        "RoHS",
        "EPEAT Gold",
        "TCO '06",
        "China RoHS",
        "Taiwan Green Mark",
        "WEEE",
        "EU RoHS",
        "Turkey RoHS",
        "Ukraine RoHS"
    ],
    "green compliant": "Yes",
    "hdmi": "Yes",
    "height": "226.1 mm",
    "horizontal viewing angle": "176\u00c2\u00b0",
    "input voltage": [
        "110 V AC",
        "220 V AC"
    ],
    "limited warranty": "3 Year",
    "manufacturer": "Lenovo Group Limited",
    "manufacturer part number": "60A9MAR2UK",
    "maximum resolution": "1920 x 1080",
    "mfr code": "60A9MAR2UK",
    "network rj45": "Yes",
    "number of screens": "1",
    "number of speakers": "2",
    "offmode power consumption": "500 mW",
    "operating power consumption": "30 W",
    "package contents": "ThinkVision LT2223d 21.5-inch FHD LED Backlit LCD OneLink Docking Monitor Detachable tool-less full ergo stand OneLink Cable VGA Cable USB Cable 135w Power Adapter + Cord CD containing multilingual user's guide, setup test pattern, and Windows installation file Quick start and safety poster",
    "panel technology": "Twisted Nematic Film (TN Film)",
    "product": "Lenovo ThinkVision LT2223d 54.6 cm\n(21.5\") LED LCD Monitor - 16:9 - 5\nms - Adjustable Display Angle -\n1920 x 1080 - 16.7 Million Colours\n- 250 cd/m\u00c3\u00af\u00c2\u00bf\u00c2\u00bd - 2,000,000:1 - Full\nHD - Speakers - Webcam - DVI - HDMI\n- VGA - USB - 30 W - Raven Black -\nENERGY STAR 6.",
    "product code": "S603PX5",
    "product line": "ThinkVision",
    "product model": "LT2223d",
    "product name": "ThinkVision LT2223d 21.5-inch FHD LED Backlit LCD OneLink Docking Monitor",
    "product type": "LCD Monitor",
    "response time": "5 ms",
    "screen mode": "Full HD",
    "screen size": "54.6 cm (21.5\")",
    "screen surface": "Anti-glare",
    "speakers": "Yes",
    "standard refresh rate": "75 Hz",
    "standby power consumption": "500 mW",
    "stock": "Call for availability",
    "swivel angle": "-45\u00c2\u00b0",
    "tilt angle": "-5\u00c2\u00b0to30\u00c2\u00b0",
    "usb": "Yes",
    "usb standard": "USB 3.0",
    "vertical viewing angle": "170\u00c2\u00b0",
    "vesa mount compatible": "Yes",
    "vesa mount standard": "100 x 100",
    "vga": "Yes",
    "webcam": "Yes",
    "weight approximate": "2.86 kg",
    "width": "348 mm"
}