{
    "<page title>": "Viewsonic VA2246M LED 22in LED LCD Monitor 16 9 5 MS 1920x1080 1000 1 1080p 766907722529 | eBay",
    "brand name": "Viewsonic",
    "certifications  standards": "CE , CB , SVHC List , UL , cUL , FCC-B / ICES-003B , TUV-S , Nemko ERGO , GOSTR+ Hygienic , UkrSEPRO , CCC , BSMI , PSB , C-tick , KC , e-standby",
    "main features": "Limited Warranty: 3 Year\nManufacturer/Supplier: Viewsonic Corporation\nManufacturer Part Number: VA2246M-LED\nManufacturer Website Address: http://www.viewsonic.com\nBrand Name: Viewsonic\nProduct Model: VA2246m-LED\nProduct Name: VA2246m-LED Widescreen LCD Monitor\nMarketing Information: The ViewSonic VA2246m-LED is a 22\" (21.5\" viewable) widescreen monitor with a LED backlight and a glossy, thin-bezel design ideal for use in the home or at the office. With Full HD 1920x1080 resolution and a 10M:1 MEGA Dynamic Contrast Ratio, the VA2246m-LED delivers stunning brightness and contrast, while a quick 5ms response time ensures crisp pictures and smooth playback. As a complete multimedia package, the display also includes a pair of integrated speakers. VGA and DVI inputs provide flexible and convenient connectivity, while a VESA-mountable design offers additional mount flexibility. With a LED backlight and energy-saving Eco-mode, the VA2246m-LED is an environmentally friendly display choice. In addition, a 3-year limited warranty, along with one of the industry's best pixel performance policies make the VA2246m-LED a great value choice for corporate and educational use as well.\nProduct Type: LCD Monitor\nNumber of Screens: 1\nScreen Size: 22\"\nScreen Mode: Full HD\nResponse Time: 5 ms\nAspect Ratio: 16:9\nHorizontal Viewing Angle: 170\u00c2\u00b0\nVertical Viewing Angle: 160\u00c2\u00b0\nAdjustable Display Angle: Yes\nMount Type: Wall Mountable\nBacklight Technology: LED\nHDCP Supported: Yes\nMaximum Resolution: 1920 x 1080\nStandard Refresh Rate: 75 Hz\nContrast Ratio: 1,000:1\nBrightness: 250 Nit\nSpeakers: Yes\nDVI: Yes\nUSB: No\nVGA: Yes\nBuilt-in Devices: Speaker\nInput Voltage: 110 V AC, 220 V AC\nOperating Power Consumption: 34 W\nVESA Mount Compatible: Yes\nVESA Mount Standard: 100 x 100\nHeight: 12.5\"\nWidth: 20.1\"\nDepth: 1.9\"\nHeight with Stand: 14.40\"\nWidth with Stand: 20.10\"\nDepth with Stand: 1.90\"\nWeight (Approximate): 6.90 lb\nWeight with Stand (Approximate): 7.70 lb\nPackage Contents:\nVA2246m-LED Widescreen LCD Monitor , Power cable , Video cable , Audio cable , Quick Start Guide , ViewSonic Wizard CD , Base instruction guide\nCertifications & Standards:\nCE , CB , SVHC List , UL , cUL , FCC-B / ICES-003B , TUV-S , Nemko ERGO , GOSTR+ Hygienic , UkrSEPRO , CCC , BSMI , PSB , C-tick , KC , e-standby\nPlatform Supported: Mac, PC\nGreen Compliant: Yes\nGreen Compliance Certificate/Authority: ENERGY STAR 5.0, RoHS, REACH, TCO Displays 5.0, ErP, China Energy Label (CEL), WEEE General Information\nManufacturer/Supplier:\nViewsonic Corporation\nManufacturer Part Number:\nVA2246M-LED\nManufacturer Website Address:\nhttp://www.viewsonic.com\nBrand Name:\nViewsonic\nProduct Model:\nVA2246m-LED\nProduct Name:\nVA2246m-LED Widescreen LCD Monitor\nMarketing Information:\nThe ViewSonic VA2246m-LED is a 22\" (21.5\" viewable) widescreen monitor with a LED backlight and a glossy, thin-bezel design ideal for use in the home or at the office. With Full HD 1920x1080 resolution and a 10M:1 MEGA Dynamic Contrast Ratio, the VA2246m-LED delivers stunning brightness and contrast, while a quick 5ms response time ensures crisp pictures and smooth playback. As a complete multimedia package, the display also includes a pair of integrated speakers. VGA and DVI inputs provide flexible and convenient connectivity, while a VESA-mountable design offers additional mount flexibility. With a LED backlight and energy-saving Eco-mode, the VA2246m-LED is an environmentally friendly display choice. In addition, a 3-year limited warranty, along with one of the industry's best pixel performance policies make the VA2246m-LED a great value choice for corporate and educational use as well.\nProduct Type:\nLCD Monitor Technical Information\nNumber of Screens:\n1\nScreen Size:\n22\"\nScreen Mode:\nFull HD\nScreen Surface:\nAnti-glare\nResponse Time:\n5 ms\nAspect Ratio:\n16:9\nHorizontal Viewing Angle:\n170\u00c2\u00b0\nVertical Viewing Angle:\n160\u00c2\u00b0\nAdjustable Display Angle:\nYes\nMount Type:\nWall Mountable\nBacklight Technology:\nLED\nHDCP Supported:\nYes Video\nMaximum Resolution:\n1920 x 1080\nStandard Refresh Rate:\n75 Hz\nContrast Ratio:\n1,000:1\nBrightness:\n250 Nit Audio\nSpeakers:\nYes Interfaces/Ports\nDVI:\nYes\nUSB:\nNo\nVGA:\nYes\nHeadphone:\nNo Built-in Devices\nBuilt-in Devices:\nSpeaker Power Description\nInput Voltage:\n110 V AC\n220 V AC\nOperating Power Consumption:\n34 W Physical Characteristics\nVESA Mount Compatible:\nYes\nVESA Mount Standard:\n100 x 100\nHeight:\n12.5\"\nWidth:\n20.1\"\nDepth:\n1.9\"\nHeight with Stand:\n14.40\"\nWidth with Stand:\n20.10\"\nDepth with Stand:\n1.90\"\nWeight (Approximate):\n6.90 lb\nWeight with Stand (Approximate):\n7.70 lb Shipping Information\nShipping Dimensions :\n4.4\" Height x 15.4\" Width x 22.2\" Depth\n:\nShipping Weight :\n9.7 lb\n:\nMiscellaneous\nPackage Contents:\nVA2246m-LED Widescreen LCD Monitor\nPower cable\nVideo cable\nAudio cable\nQuick Start Guide\nViewSonic Wizard CD\nBase instruction guide\nCertifications & Standards:\nCE\nCB\nSVHC List\nUL\ncUL\nFCC-B / ICES-003B\nTUV-S\nNemko ERGO\nGOSTR+ Hygienic\nUkrSEPRO\nCCC\nBSMI\nPSB\nC-tick\nKC\ne-standby\nPlatform Supported:\nMac\nPC\nGreen Compliant:\nYes\nGreen Compliance Certificate/Authority:\nENERGY STAR 5.0\nRoHS\nREACH\nTCO Displays 5.0\nErP\nChina Energy Label (CEL)\nWEEE Warranty\nLimited Warranty:\n3 Year",
    "manufacturer part number": "VA2246M-LED",
    "manufacturer website address": "http://www.viewsonic.com",
    "manufacturersupplier": "Viewsonic Corporation",
    "marketing information": "The ViewSonic VA2246m-LED is a 22\" (21.5\" viewable) widescreen monitor with a LED backlight and a glossy, thin-bezel design ideal for use in the home or at the office. With Full HD 1920x1080 resolution and a 10M:1 MEGA Dynamic Contrast Ratio, the VA2246m-LED delivers stunning brightness and contrast, while a quick 5ms response time ensures crisp pictures and smooth playback. As a complete multimedia package, the display also includes a pair of integrated speakers. VGA and DVI inputs provide flexible and convenient connectivity, while a VESA-mountable design offers additional mount flexibility. With a LED backlight and energy-saving Eco-mode, the VA2246m-LED is an environmentally friendly display choice. In addition, a 3-year limited warranty, along with one of the industry's best pixel performance policies make the VA2246m-LED a great value choice for corporate and educational use as well.",
    "package contents": "VA2246m-LED Widescreen LCD Monitor , Power cable , Video cable , Audio cable , Quick Start Guide , ViewSonic Wizard CD , Base instruction guide",
    "product model": "VA2246m-LED",
    "product name": "VA2246m-LED Widescreen LCD Monitor",
    "product type": "LCD Monitor"
}