{
    "<page title>": "Viewsonic VX2770SMH LED 27\" LED LCD Monitor 7 MS 1920x1080 1080p HDMI DVI VGA 766907659719 | eBay",
    "brand name": "Viewsonic",
    "certifications  standards": "CE, CB, BSMI, SASO, C-tick, e-standby, KC, UL/cUL, FCC-B, ICES003, NOM, GOST-R/Hygienic, UkrSEPRO, CCC, ISO 9001, ISO 14001, TUV",
    "general information": "Manufacturer/Supplier:\nViewsonic Corporation\nManufacturer Part Number:\nVX2770SMH-LED\nManufacturer Website Address:\nwww.viewsonic.com\nBrand Name:\nViewsonic\nProduct Model:\nVX2770Smh-LED\nProduct Name:\nVX2770Smh-LED Widescreen With Full HD 1080p 27\" Frameless LED Display\nMarketing Information:\nThe ViewSonic\u00c2\u00ae VX2770Smh-LED features an LED backlit 27\" frameless design widescreen monitor with up to 40%* energy savings compared to a regular 27\" monitor. The environmentally-friendly mercury-free VX2770Smh-LED offers Full HD 1920x1080 resolution, HDMI\u00c2\u00ae and DVI with HDCP and VGA inputs, external power supply, SRS Premium Sound\u00c2\u00ae, and 30,000,000:1 MEGA Dynamic Contrast Ratio. A stylish glossy ID and thin profile combine to make it the center piece of your home or office. The SuperClear\u00c2\u00ae IPS panel with wide viewing angles and high contrast ratio deliver extraordinary visual clarity, making VX2770Smh-LED an excellent choice for entertainment and gaming. A 3-year limited warranty, the industry's best pixel performance policy, energy saving Eco-mode and Windows\u00c2\u00ae 7 certification help ensure the product quality for years to come.\nProduct Type:\nLCD Monitor Technical Information\nNumber of Screens:\n1\nScreen Size:\n27\"\nScreen Mode:\nFull HD\nScreen Surface:\nAnti-glare\nResponse Time:\n7 ms\nHorizontal Viewing Angle:\n178\u00c2\u00b0\nVertical Viewing Angle:\n178\u00c2\u00b0\nAdjustable Display Angle:\nYes\nBacklight Technology:\nLED\nHDCP Supported:\nYes\nFeatures:\nSecurity Lock\nIn-plane Switching (IPS) Technology\nTouch Controls Video\nMaximum Resolution:\n1920 x 1080\nStandard Refresh Rate:\n76 Hz\nContrast Ratio:\n1,000:1\nBrightness:\n250 Nit Interfaces/Ports\nDVI:\nYes\nHDMI:\nYes\nVGA:\nYes Power Description\nInput Voltage:\n110 V AC\n220 V AC\nOperating Power Consumption:\n30 W Physical Characteristics\nHeight:\n18.1\"\nWidth:\n24.5\"\nDepth:\n7.6\"\nWeight (Approximate):\n11.00 lb Shipping Information\nShipping Dimensions :\n20.75\" Height x 7.0\" Width x 26.0\" Depth\nCase Pack Qty :\n1\nShipping Weight :\n32.0 lb\nMiscellaneous\nPackage Contents:\nVX2770Smh-LED Widescreen With Full HD 1080p 27\" Frameless LED Display\nPower Cable\nAC/DC Adapter\nVGA Cable\nHDMI Cable\nQuick Start Guide\nViewSonic Wizard CD\nCertifications & Standards:\nCE\nCB\nBSMI\nSASO\nC-tick\ne-standby\nKC\nUL/cUL\nFCC-B\nICES003\nNOM\nGOST-R/Hygienic\nUkrSEPRO\nCCC\nISO 9001\nISO 14001\nTUV\nPlatform Supported:\nPC\nMac\nGreen Compliant:\nYes\nGreen Compliance Certificate/Authority:\nEnergy Star\nErP\nEPEAT Silver\nWEEE\nRoHS Warranty\nLimited Warranty:\n3 Year",
    "main features": "Limited Warranty: 3 Year\nManufacturer/Supplier: Viewsonic Corporation\nManufacturer Part Number: VX2770SMH-LED\nManufacturer Website Address: www.viewsonic.com\nBrand Name: Viewsonic\nProduct Model: VX2770Smh-LED\nProduct Name: VX2770Smh-LED Widescreen With Full HD 1080p 27\" Frameless LED Display\nMarketing Information: The ViewSonic\u00c2\u00ae VX2770Smh-LED features an LED backlit 27\" frameless design widescreen monitor with up to 40%* energy savings compared to a regular 27\" monitor. The environmentally-friendly mercury-free VX2770Smh-LED offers Full HD 1920x1080 resolution, HDMI\u00c2\u00ae and DVI with HDCP and VGA inputs, external power supply, SRS Premium Sound\u00c2\u00ae, and 30,000,000:1 MEGA Dynamic Contrast Ratio. A stylish glossy ID and thin profile combine to make it the center piece of your home or office. The SuperClear\u00c2\u00ae IPS panel with wide viewing angles and high contrast ratio deliver extraordinary visual clarity, making VX2770Smh-LED an excellent choice for entertainment and gaming. A 3-year limited warranty, the industry's best pixel performance policy, energy saving Eco-mode and Windows\u00c2\u00ae 7 certification help ensure the product quality for years to come.\nProduct Type: LCD Monitor\nNumber of Screens: 1\nScreen Size: 27\"\nScreen Mode: Full HD\nResponse Time: 7 ms\nHorizontal Viewing Angle: 178\u00c2\u00b0\nVertical Viewing Angle: 178\u00c2\u00b0\nAdjustable Display Angle: Yes\nBacklight Technology: LED\nHDCP Supported: Yes\nFeatures: Security Lock, In-plane Switching (IPS) Technology, Touch Controls\nMaximum Resolution: 1920 x 1080\nStandard Refresh Rate: 76 Hz\nContrast Ratio: 1,000:1\nBrightness: 250 Nit\nDVI: Yes\nHDMI: Yes\nVGA: Yes\nInput Voltage: 110 V AC, 220 V AC\nOperating Power Consumption: 30 W\nHeight: 18.1\"\nWidth: 24.5\"\nDepth: 7.6\"\nWeight (Approximate): 11.00 lb\nPackage Contents:\nVX2770Smh-LED Widescreen With Full HD 1080p 27\" Frameless LED Display, Power Cable, AC/DC Adapter, VGA Cable, HDMI Cable, Quick Start Guide, ViewSonic Wizard CD\nCertifications & Standards:\nCE, CB, BSMI, SASO, C-tick, e-standby, KC, UL/cUL, FCC-B, ICES003, NOM, GOST-R/Hygienic, UkrSEPRO, CCC, ISO 9001, ISO 14001, TUV\nPlatform Supported: PC, Mac\nGreen Compliant: Yes\nGreen Compliance Certificate/Authority: Energy Star, ErP, EPEAT Silver, WEEE, RoHS\nGeneral Information\nManufacturer/Supplier:\nViewsonic Corporation\nManufacturer Part Number:\nVX2770SMH-LED\nManufacturer Website Address:\nwww.viewsonic.com\nBrand Name:\nViewsonic\nProduct Model:\nVX2770Smh-LED\nProduct Name:\nVX2770Smh-LED Widescreen With Full HD 1080p 27\" Frameless LED Display\nMarketing Information:\nThe ViewSonic\u00c2\u00ae VX2770Smh-LED features an LED backlit 27\" frameless design widescreen monitor with up to 40%* energy savings compared to a regular 27\" monitor. The environmentally-friendly mercury-free VX2770Smh-LED offers Full HD 1920x1080 resolution, HDMI\u00c2\u00ae and DVI with HDCP and VGA inputs, external power supply, SRS Premium Sound\u00c2\u00ae, and 30,000,000:1 MEGA Dynamic Contrast Ratio. A stylish glossy ID and thin profile combine to make it the center piece of your home or office. The SuperClear\u00c2\u00ae IPS panel with wide viewing angles and high contrast ratio deliver extraordinary visual clarity, making VX2770Smh-LED an excellent choice for entertainment and gaming. A 3-year limited warranty, the industry's best pixel performance policy, energy saving Eco-mode and Windows\u00c2\u00ae 7 certification help ensure the product quality for years to come.\nProduct Type:\nLCD Monitor\nTechnical Information\nNumber of Screens:\n1\nScreen Size:\n27\"\nScreen Mode:\nFull HD\nScreen Surface:\nAnti-glare\nResponse Time:\n7 ms\nHorizontal Viewing Angle:\n178\u00c2\u00b0\nVertical Viewing Angle:\n178\u00c2\u00b0\nAdjustable Display Angle:\nYes\nBacklight Technology:\nLED\nHDCP Supported:\nYes\nFeatures:\nSecurity Lock\nIn-plane Switching (IPS) Technology\nTouch Controls\nVideo\nMaximum Resolution:\n1920 x 1080\nStandard Refresh Rate:\n76 Hz\nContrast Ratio:\n1,000:1\nBrightness:\n250 Nit\nInterfaces/Ports\nDVI:\nYes\nHDMI:\nYes\nVGA:\nYes\nPower Description\nInput Voltage:\n110 V AC\n220 V AC\nOperating Power Consumption:\n30 W\nPhysical Characteristics\nHeight:\n18.1\"\nWidth:\n24.5\"\nDepth:\n7.6\"\nWeight (Approximate):\n11.00 lb\nShipping Information\nShipping Dimensions :\n20.75\" Height x 7.0\" Width x 26.0\" Depth\nCase Pack Qty :\n1\nShipping Weight :\n32.0 lb\nMiscellaneous\nPackage Contents:\nVX2770Smh-LED Widescreen With Full HD 1080p 27\" Frameless LED Display\nPower Cable\nAC/DC Adapter\nVGA Cable\nHDMI Cable\nQuick Start Guide\nViewSonic Wizard CD\nCertifications & Standards:\nCE\nCB\nBSMI\nSASO\nC-tick\ne-standby\nKC\nUL/cUL\nFCC-B\nICES003\nNOM\nGOST-R/Hygienic\nUkrSEPRO\nCCC\nISO 9001\nISO 14001\nTUV\nPlatform Supported:\nPC\nMac\nGreen Compliant:\nYes\nGreen Compliance Certificate/Authority:\nEnergy Star\nErP\nEPEAT Silver\nWEEE\nRoHS\nWarranty\nLimited Warranty:\n3 Year",
    "manufacturer part number": "VX2770SMH-LED",
    "manufacturer website address": "www.viewsonic.com",
    "manufacturersupplier": "Viewsonic Corporation",
    "marketing information": "The ViewSonic\u00c2\u00ae VX2770Smh-LED features an LED backlit 27\" frameless design widescreen monitor with up to 40%* energy savings compared to a regular 27\" monitor. The environmentally-friendly mercury-free VX2770Smh-LED offers Full HD 1920x1080 resolution, HDMI\u00c2\u00ae and DVI with HDCP and VGA inputs, external power supply, SRS Premium Sound\u00c2\u00ae, and 30,000,000:1 MEGA Dynamic Contrast Ratio. A stylish glossy ID and thin profile combine to make it the center piece of your home or office. The SuperClear\u00c2\u00ae IPS panel with wide viewing angles and high contrast ratio deliver extraordinary visual clarity, making VX2770Smh-LED an excellent choice for entertainment and gaming. A 3-year limited warranty, the industry's best pixel performance policy, energy saving Eco-mode and Windows\u00c2\u00ae 7 certification help ensure the product quality for years to come.",
    "package contents": "VX2770Smh-LED Widescreen With Full HD 1080p 27\" Frameless LED Display, Power Cable, AC/DC Adapter, VGA Cable, HDMI Cable, Quick Start Guide, ViewSonic Wizard CD",
    "product model": "VX2770Smh-LED",
    "product name": "VX2770Smh-LED Widescreen With Full HD 1080p 27\" Frameless LED Display",
    "product type": "LCD Monitor"
}