{
    "<page title>": "Viewsonic VA2251M 22in CCFL LCD Monitor 16 9 5 MS VA2251M TAA 1920x1080 1080p 766907613018 | eBay",
    "brand name": "Viewsonic",
    "certifications  standards": "UL/cUL , FCC-B, , Mexico Energy , NOM , ISO 9001 , ISO 14001 , CE , CB , TAA",
    "main features": "Manufacturer: Viewsonic Corporation\nManufacturer Part Number: VA2251M-TAA\nManufacturer Website Address: www.viewsonic.com\nBrand Name: Viewsonic\nProduct Model: VA2251m\nProduct Name: 22\" Full HD 1080p LED Monitor Great Value and Picture Perfect\nMarketing Information: ViewSonic's new 22-inch VA2251m is eco-friendly and produces a Full HD 1080p viewing experience. Featuring a widescreen Full HD 1080p 1920 x 1080 resolution, the VA2251m series delivers crisp images for work and home environments. An incorporated LED backlight as well as a power-saving ECO-mode produces higher levels of brightness and refines image details even in low light conditions. Reducing power consumption with three different brightness throughputs, helps to save on energy and accommodate different environments. Built-in sRGB color correction technology and dynamic contrast ratio also manage pixel quality to the finest detail and produces a great viewing experience.\nProduct Type: LCD Monitor\nNumber of Screens: 1\nScreen Size: 22\"\nScreen Mode: Full HD\nResponse Time: 5 ms\nAspect Ratio: 16:9\nHorizontal Viewing Angle: 170\u00c2\u00b0\nVertical Viewing Angle: 160\u00c2\u00b0\nAdjustable Display Angle: Yes\nMount Type: Wall Mountable\nBacklight Technology: CCFL\nHDCP Supported: Yes\nMaximum Resolution: 1920 x 1080\nStandard Refresh Rate: 75 Hz\nContrast Ratio: 1,000:1\nBrightness: 250 Nit\nSpeakers: Yes\nDVI: Yes\nVGA: Yes\nBuilt-in Devices: Speaker\nInput Voltage: 110 V AC, 220 V AC\nOperating Power Consumption: 26 W\nVESA Mount Compatible: Yes\nVESA Mount Standard: 100 x 100\nColor: Black\nHeight: 12.2\"\nWidth: 20.0\"\nDepth: 2.4\"\nHeight with Stand: 14.60\"\nWidth with Stand: 20\"\nDepth with Stand: 6.50\"\nWeight (Approximate): 7.05 lb\nWeight with Stand (Approximate): 7.72 lb\nPackage Contents:\n22\" Full HD 1080p LED Monitor Great Value and Picture Perfect , Power Cable , VGA Cable , Audio Cable , Quick Start Guide ViewSonic Wizard , CD (User Guide and Drivers)\nCertifications & Standards:\nUL/cUL , FCC-B, , Mexico Energy , NOM , ISO 9001 , ISO 14001 , CE , CB , TAA\nPlatform Supported: PC, Mac\nGreen Compliant: Yes\nGreen Compliance Certificate/Authority: Energy Star, EPEAT Silver, WEEE, RoHS\nCountry of Origin: Mexico\nStandard Warranty: 3 Year Limited General Information\nManufacturer:\nViewsonic Corporation\nManufacturer Part Number:\nVA2251M-TAA\nManufacturer Website Address:\nhttp://www.viewsonic.com/\nBrand Name:\nViewsonic\nProduct Model:\nVA2251m\nProduct Name:\n22\" Full HD 1080p LED Monitor Great Value and Picture Perfect\nMarketing Information:\nViewSonic's new 22-inch VA2251m is eco-friendly and produces a Full HD 1080p viewing experience. Featuring a widescreen Full HD 1080p 1920 x 1080 resolution, the VA2251m series delivers crisp images for work and home environments. An incorporated LED backlight as well as a power-saving ECO-mode produces higher levels of brightness and refines image details even in low light conditions. Reducing power consumption with three different brightness throughputs, helps to save on energy and accommodate different environments. Built-in sRGB color correction technology and dynamic contrast ratio also manage pixel quality to the finest detail and produces a great viewing experience.\nProduct Type:\nLCD Monitor Technical Information\nNumber of Screens:\n1\nScreen Size:\n22\"\nScreen Mode:\nFull HD\nScreen Surface:\nAnti-glare\nResponse Time:\n5 ms\nAspect Ratio:\n16:9\nHorizontal Viewing Angle:\n170\u00c2\u00b0\nVertical Viewing Angle:\n160\u00c2\u00b0\nAdjustable Display Angle:\nYes\nMount Type:\nWall Mountable\nBacklight Technology:\nCCFL\nHDCP Supported:\nYes\nFeatures:\nSecurity Lock Video\nMaximum Resolution:\n1920 x 1080\nStandard Refresh Rate:\n75 Hz\nContrast Ratio:\n1,000:1\nBrightness:\n250 Nit Audio\nNumber of Speakers:\n2\nSpeakers:\nYes Interfaces/Ports\nDVI:\nYes\nVGA:\nYes Built-in Devices\nBuilt-in Devices:\nSpeaker Power Description\nInput Voltage:\n110 V AC\n220 V AC\nOperating Power Consumption:\n26 W Physical Characteristics\nVESA Mount Compatible:\nYes\nVESA Mount Standard:\n100 x 100\nColor:\nBlack\nHeight:\n12.2\"\nWidth:\n20.0\"\nDepth:\n2.4\"\nHeight with Stand:\n14.60\"\nWidth with Stand:\n20\"\nDepth with Stand:\n6.50\"\nWeight (Approximate):\n7.05 lb\nWeight with Stand (Approximate):\n7.72 lb Shipping Information\nShipping Dimensions :\n5.2\" Height x 16.5\" Width x 22.2\" Depth\n:\nShipping Weight :\n10.15 lb\n:\nMiscellaneous\nPackage Contents:\n22\" Full HD 1080p LED Monitor Great Value and Picture Perfect\nPower Cable\nVGA Cable\nAudio Cable\nQuick Start Guide ViewSonic Wizard\nCD (User Guide and Drivers)\nCertifications & Standards:\nUL/cUL\nFCC-B,\nMexico Energy\nNOM\nISO 9001\nISO 14001\nCE\nCB\nTAA\nPlatform Supported:\nPC\nMac\nGreen Compliant:\nYes\nGreen Compliance Certificate/Authority:\nEnergy Star\nEPEAT Silver\nWEEE\nRoHS\nCountry of Origin:\nMexico Warranty\nStandard Warranty:\n3 Year Limited",
    "manufacturer": "Viewsonic Corporation",
    "manufacturer part number": "VA2251M-TAA",
    "manufacturer website address": "http://www.viewsonic.com/",
    "marketing information": "ViewSonic's new 22-inch VA2251m is eco-friendly and produces a Full HD 1080p viewing experience. Featuring a widescreen Full HD 1080p 1920 x 1080 resolution, the VA2251m series delivers crisp images for work and home environments. An incorporated LED backlight as well as a power-saving ECO-mode produces higher levels of brightness and refines image details even in low light conditions. Reducing power consumption with three different brightness throughputs, helps to save on energy and accommodate different environments. Built-in sRGB color correction technology and dynamic contrast ratio also manage pixel quality to the finest detail and produces a great viewing experience.",
    "package contents": "22\" Full HD 1080p LED Monitor Great Value and Picture Perfect , Power Cable , VGA Cable , Audio Cable , Quick Start Guide ViewSonic Wizard , CD (User Guide and Drivers)",
    "product model": "VA2251m",
    "product name": "22\" Full HD 1080p LED Monitor Great Value and Picture Perfect",
    "product type": "LCD Monitor"
}