{
    "<page title>": "Viewsonic Value VA2342 LED 23\" LED LCD Monitor 16 9 5 MS 766907648317 | eBay",
    "brand name": "Viewsonic",
    "certifications  standards": "UL, CUL, FCC-B (ICES), CB, CCC, NOM, CE, TUV",
    "general information": "Manufacturer/Supplier:\nViewsonic Corporation\nManufacturer Part Number:\nVA2342-LED\nManufacturer Website Address:\nwww.viewsonic.com\nBrand Name:\nViewsonic\nProduct Line:\nValue\nProduct Model:\nVA2342-LED\nProduct Name:\nVA2342-LED 23\" Full HD 1080p LED Monitor\nMarketing Information:\nThe ViewSonic\u00c2\u00ae VA2432-LED comes equipped with a long-lasting and highly efficient power-saving LED backlight as well as ViewSonic's exclusive Eco-mode that reduces power consumption based on different lighting environments and minimizes maintenance efforts and costs. With a 1920 x 1080 Full HD 1080p resolution, the image performance has never been this perfect; the 16:9 screen size supports multi-screen functionality for enhanced work productivity. Embedded dynamic contrast ratio technology not only enhances the dark and bright contrast of images but helps to produce an ultrahigh 10,000,000:1 ratio to deliver perfect image performance. Built-in sRGB color correction technologies revives image colors and captures the most realistic aspects of content for consistent color performing presentations, photographs, graphic designs or printings. With an incorporated slim bezel, hidden button design and patented VESA\u00c2\u00ae wall mount compliance, the VA2432- LED serves as a perfectly functional display for your office or home settings.\nProduct Type:\nLCD Monitor Technical Information\nNumber of Screens:\n1\nScreen Size:\n23\"\nScreen Mode:\nFull HD\nScreen Surface:\nAnti-glare\nResponse Time:\n5 ms\nAspect Ratio:\n16:9\nHorizontal Viewing Angle:\n170\u00c2\u00b0\nVertical Viewing Angle:\n160\u00c2\u00b0\nAdjustable Display Angle:\nYes\nMount Type:\nWall Mountable\nBacklight Technology:\nLED\nHDCP Supported:\nYes\nFeatures:\nSecurity Lock Video\nMaximum Resolution:\n1920 x 1080\nStandard Refresh Rate:\n60 Hz\nContrast Ratio:\n1,000:1\nBrightness:\n250 Nit Interfaces/Ports\nDVI:\nYes\nVGA:\nYes Power Description\nInput Voltage:\n110 V AC\n220 V AC\nOperating Power Consumption:\n22 W Physical Characteristics\nVESA Mount Compatible:\nYes\nVESA Mount Standard:\n100 x 100\nColor:\nBlack\nHeight:\n13.1\"\nWidth:\n21.6\"\nDepth:\n1.5\"\nHeight with Stand:\n16.90\"\nWidth with Stand:\n21.60\"\nDepth with Stand:\n7.90\"\nWeight (Approximate):\n5.00 lb\nWeight with Stand (Approximate):\n5.60 lb Shipping Information\nShipping Dimensions :\n4.5\" Height x 15.5\" Width x 23.5\" Depth\nCase Pack Qty :\n1\nShipping Weight :\n8.2 lb\n:\nMiscellaneous\nPackage Contents:\nVA2342-LED 23\" Full HD 1080p LED Monitor\nPower Adapter\nPower Cable\nVGA Video Cable\nViewSonic Wizard CD-ROM\nQuick Start Guide\nCertifications & Standards:\nUL\nCUL\nFCC-B (ICES)\nCB\nCCC\nNOM\nCE\nTUV\nPlatform Supported:\nPC\nMac\nGreen Compliant:\nYes\nGreen Compliance Certificate/Authority:\nChina Energy Label (CEL)\nRoHS\nWEEE\nEnergy Star 5.0\nEPEAT Silver Warranty\nLimited Warranty:\n3 Year",
    "main features": "Limited Warranty: 3 Year\nManufacturer/Supplier: Viewsonic Corporation\nManufacturer Part Number: VA2342-LED\nManufacturer Website Address: www.viewsonic.com\nBrand Name: Viewsonic\nProduct Line: Value\nProduct Model: VA2342-LED\nProduct Name: VA2342-LED 23\" Full HD 1080p LED Monitor\nMarketing Information: The ViewSonic\u00c2\u00ae VA2432-LED comes equipped with a long-lasting and highly efficient power-saving LED backlight as well as ViewSonic's exclusive Eco-mode that reduces power consumption based on different lighting environments and minimizes maintenance efforts and costs. With a 1920 x 1080 Full HD 1080p resolution, the image performance has never been this perfect; the 16:9 screen size supports multi-screen functionality for enhanced work productivity. Embedded dynamic contrast ratio technology not only enhances the dark and bright contrast of images but helps to produce an ultrahigh 10,000,000:1 ratio to deliver perfect image performance. Built-in sRGB color correction technologies revives image colors and captures the most realistic aspects of content for consistent color performing presentations, photographs, graphic designs or printings. With an incorporated slim bezel, hidden button design and patented VESA\u00c2\u00ae wall mount compliance, the VA2432- LED serves as a perfectly functional display for your office or home settings.\nProduct Type: LCD Monitor\nNumber of Screens: 1\nScreen Size: 23\"\nScreen Mode: Full HD\nResponse Time: 5 ms\nAspect Ratio: 16:9\nHorizontal Viewing Angle: 170\u00c2\u00b0\nVertical Viewing Angle: 160\u00c2\u00b0\nAdjustable Display Angle: Yes\nMount Type: Wall Mountable\nBacklight Technology: LED\nHDCP Supported: Yes\nFeatures: Security Lock\nMaximum Resolution: 1920 x 1080\nStandard Refresh Rate: 60 Hz\nContrast Ratio: 1,000:1\nBrightness: 250 Nit\nDVI: Yes\nVGA: Yes\nInput Voltage: 110 V AC, 220 V AC\nOperating Power Consumption: 22 W\nVESA Mount Compatible: Yes\nVESA Mount Standard: 100 x 100\nColor: Black\nHeight: 13.1\"\nWidth: 21.6\"\nDepth: 1.5\"\nHeight with Stand: 16.90\"\nWidth with Stand: 21.60\"\nDepth with Stand: 7.90\"\nWeight (Approximate): 5.00 lb\nWeight with Stand (Approximate): 5.60 lb\nPackage Contents:\nVA2342-LED 23\" Full HD 1080p LED Monitor, Power Adapter, Power Cable, VGA Video Cable, ViewSonic Wizard CD-ROM, Quick Start Guide\nCertifications & Standards:\nUL, CUL, FCC-B (ICES), CB, CCC, NOM, CE, TUV\nPlatform Supported: PC, Mac\nGreen Compliant: Yes\nGreen Compliance Certificate/Authority: China Energy Label (CEL), RoHS, WEEE, Energy Star 5.0, EPEAT Silver\nGeneral Information\nManufacturer/Supplier:\nViewsonic Corporation\nManufacturer Part Number:\nVA2342-LED\nManufacturer Website Address:\nwww.viewsonic.com\nBrand Name:\nViewsonic\nProduct Line:\nValue\nProduct Model:\nVA2342-LED\nProduct Name:\nVA2342-LED 23\" Full HD 1080p LED Monitor\nMarketing Information:\nThe ViewSonic\u00c2\u00ae VA2432-LED comes equipped with a long-lasting and highly efficient power-saving LED backlight as well as ViewSonic's exclusive Eco-mode that reduces power consumption based on different lighting environments and minimizes maintenance efforts and costs. With a 1920 x 1080 Full HD 1080p resolution, the image performance has never been this perfect; the 16:9 screen size supports multi-screen functionality for enhanced work productivity. Embedded dynamic contrast ratio technology not only enhances the dark and bright contrast of images but helps to produce an ultrahigh 10,000,000:1 ratio to deliver perfect image performance. Built-in sRGB color correction technologies revives image colors and captures the most realistic aspects of content for consistent color performing presentations, photographs, graphic designs or printings. With an incorporated slim bezel, hidden button design and patented VESA\u00c2\u00ae wall mount compliance, the VA2432- LED serves as a perfectly functional display for your office or home settings.\nProduct Type:\nLCD Monitor\nTechnical Information\nNumber of Screens:\n1\nScreen Size:\n23\"\nScreen Mode:\nFull HD\nScreen Surface:\nAnti-glare\nResponse Time:\n5 ms\nAspect Ratio:\n16:9\nHorizontal Viewing Angle:\n170\u00c2\u00b0\nVertical Viewing Angle:\n160\u00c2\u00b0\nAdjustable Display Angle:\nYes\nMount Type:\nWall Mountable\nBacklight Technology:\nLED\nHDCP Supported:\nYes\nFeatures:\nSecurity Lock\nVideo\nMaximum Resolution:\n1920 x 1080\nStandard Refresh Rate:\n60 Hz\nContrast Ratio:\n1,000:1\nBrightness:\n250 Nit\nInterfaces/Ports\nDVI:\nYes\nVGA:\nYes\nPower Description\nInput Voltage:\n110 V AC\n220 V AC\nOperating Power Consumption:\n22 W\nPhysical Characteristics\nVESA Mount Compatible:\nYes\nVESA Mount Standard:\n100 x 100\nColor:\nBlack\nHeight:\n13.1\"\nWidth:\n21.6\"\nDepth:\n1.5\"\nHeight with Stand:\n16.90\"\nWidth with Stand:\n21.60\"\nDepth with Stand:\n7.90\"\nWeight (Approximate):\n5.00 lb\nWeight with Stand (Approximate):\n5.60 lb\nShipping Information\nShipping Dimensions :\n4.5\" Height x 15.5\" Width x 23.5\" Depth\nCase Pack Qty :\n1\nShipping Weight :\n8.2 lb\n:\nMiscellaneous\nPackage Contents:\nVA2342-LED 23\" Full HD 1080p LED Monitor\nPower Adapter\nPower Cable\nVGA Video Cable\nViewSonic Wizard CD-ROM\nQuick Start Guide\nCertifications & Standards:\nUL\nCUL\nFCC-B (ICES)\nCB\nCCC\nNOM\nCE\nTUV\nPlatform Supported:\nPC\nMac\nGreen Compliant:\nYes\nGreen Compliance Certificate/Authority:\nChina Energy Label (CEL)\nRoHS\nWEEE\nEnergy Star 5.0\nEPEAT Silver\nWarranty\nLimited Warranty:\n3 Year",
    "manufacturer part number": "VA2342-LED",
    "manufacturer website address": "www.viewsonic.com",
    "manufacturersupplier": "Viewsonic Corporation",
    "marketing information": "The ViewSonic\u00c2\u00ae VA2432-LED comes equipped with a long-lasting and highly efficient power-saving LED backlight as well as ViewSonic's exclusive Eco-mode that reduces power consumption based on different lighting environments and minimizes maintenance efforts and costs. With a 1920 x 1080 Full HD 1080p resolution, the image performance has never been this perfect; the 16:9 screen size supports multi-screen functionality for enhanced work productivity. Embedded dynamic contrast ratio technology not only enhances the dark and bright contrast of images but helps to produce an ultrahigh 10,000,000:1 ratio to deliver perfect image performance. Built-in sRGB color correction technologies revives image colors and captures the most realistic aspects of content for consistent color performing presentations, photographs, graphic designs or printings. With an incorporated slim bezel, hidden button design and patented VESA\u00c2\u00ae wall mount compliance, the VA2432- LED serves as a perfectly functional display for your office or home settings.",
    "package contents": "VA2342-LED 23\" Full HD 1080p LED Monitor, Power Adapter, Power Cable, VGA Video Cable, ViewSonic Wizard CD-ROM, Quick Start Guide",
    "product line": "Value",
    "product model": "VA2342-LED",
    "product name": "VA2342-LED 23\" Full HD 1080p LED Monitor",
    "product type": "LCD Monitor"
}