{
    "<page title>": "AOC Professional E2260SWDA 21 5in LED LCD Monitor 16 9 5 MS E2260SWDA | eBay",
    "brand name": "AOC",
    "main features": "Manufacturer: AOC\nManufacturer Part Number: E2260SWDA\nManufacturer Website Address: www.aocmonitor.com\nBrand Name: AOC\nProduct Line: Professional\nProduct Model: e2260Swda\nProduct Name: LED Monitor - e2260Swda Professional 54.7cm (21.5\")\nMarketing Information: This model targets business and home office users alike. Hidden behind its classically designed case is the latest LED technology.It boasts a high typical contrast, an ultra-fast response time and wide viewing angles for excellent imaging performance.With the i-Care function, the monitor adapts the panel's brightness to the ambient light. This means a more comfortable viewing experience, whilst lowering the energyconsumption at the same time. The environmentally friendly display comes in an elegant, textured black finish.\nProduct Type: LCD Monitor\nNumber of Screens: 1\nScreen Size: 21.5\"\nScreen Mode: Full HD\nResponse Time: 5 ms\nAspect Ratio: 16:9\nHorizontal Viewing Angle: 170\u00c2\u00b0\nVertical Viewing Angle: 160\u00c2\u00b0\nAdjustable Display Angle: Yes\nAdjustable Display Height: No\nAdjustable Display Pivot: No\nMount Type: Wall Mountable\nBacklight Technology: LED\nHDCP Supported: Yes\nFeatures: Security Lock\nMaximum Resolution: 1920 x 1080\nColor Supported: 16.7 Million Colors\nContrast Ratio: 1,000:1\nBrightness: 250 Nit\nSpeakers: Yes\nDVI: Yes\nHDMI: No\nVGA: Yes\nDisplayPort: No\nBuilt-in Devices: Speaker\nVESA Mount Compatible: Yes\nVESA Mount Standard: 100 x 100\nColor: Black\nHeight: 14.7\"\nWidth: 20.1\"\nDepth: 7.3\"\nPlatform Supported: PC General Information\nManufacturer:\nAOC\nManufacturer Part Number:\nE2260SWDA\nManufacturer Website Address:\nwww.aocmonitor.com\nBrand Name:\nAOC\nProduct Line:\nProfessional\nProduct Model:\ne2260Swda\nProduct Name:\nLED Monitor - e2260Swda Professional 54.7cm (21.5\")\nMarketing Information:\nThis model targets business and home office users alike. Hidden behind its classically designed case is the latest LED technology.It boasts a high typical contrast, an ultra-fast response time and wide viewing angles for excellent imaging performance.With the i-Care function, the monitor adapts the panel's brightness to the ambient light. This means a more comfortable viewing experience, whilst lowering the energyconsumption at the same time. The environmentally friendly display comes in an elegant, textured black finish.\nProduct Type:\nLCD Monitor Technical Information\nNumber of Screens:\n1\nScreen Size:\n21.5\"\nScreen Mode:\nFull HD\nResponse Time:\n5 ms\nAspect Ratio:\n16:9\nHorizontal Viewing Angle:\n170\u00c2\u00b0\nVertical Viewing Angle:\n160\u00c2\u00b0\nAdjustable Display Angle:\nYes\nAdjustable Display Height:\nNo\nAdjustable Display Pivot:\nNo\nMount Type:\nWall Mountable\nBacklight Technology:\nLED\nHDCP Supported:\nYes\nFeatures:\nSecurity Lock Video\nMaximum Resolution:\n1920 x 1080\nColor Supported:\n16.7 Million Colors\nContrast Ratio:\n1,000:1\nBrightness:\n250 Nit Audio\nSpeakers:\nYes Interfaces/Ports\nDVI:\nYes\nHDMI:\nNo\nVGA:\nYes\nDisplayPort:\nNo Built-in Devices\nBuilt-in Devices:\nSpeaker Physical Characteristics\nVESA Mount Compatible:\nYes\nVESA Mount Standard:\n100 x 100\nColor:\nBlack\nHeight:\n14.7\"\nWidth:\n20.1\"\nDepth:\n7.3\" Shipping Information\nShipping Dimensions :\n4.5\" Height x 17.2\" Width x 22.2\" Depth\n:\nShipping Weight :\n8.6 lb\n:\nMiscellaneous\nPlatform Supported:\nPC",
    "manufacturer": "AOC",
    "manufacturer part number": "E2260SWDA",
    "manufacturer website address": "www.aocmonitor.com",
    "marketing information": "This model targets business and home office users alike. Hidden behind its classically designed case is the latest LED technology.It boasts a high typical contrast, an ultra-fast response time and wide viewing angles for excellent imaging performance.With the i-Care function, the monitor adapts the panel's brightness to the ambient light. This means a more comfortable viewing experience, whilst lowering the energyconsumption at the same time. The environmentally friendly display comes in an elegant, textured black finish.",
    "product line": "Professional",
    "product model": "e2260Swda",
    "product name": "LED Monitor - e2260Swda Professional 54.7cm (21.5\")",
    "product type": "LCD Monitor"
}