{
    "<page title>": "Viewsonic VA2703 LED 27\" LED LCD Monitor 16 9 3 MS | eBay",
    "brand name": "Viewsonic",
    "general information": "Manufacturer/Supplier:\nViewsonic Corporation\nManufacturer Part Number:\nVA2703-LED\nManufacturer Website Address:\nwww.viewsonic.com\nBrand Name:\nViewsonic\nProduct Series:\nVA\nProduct Model:\nVA2703-LED\nProduct Name:\nVA2703-LED Widescreen LCD Monitor\nMarketing Information:\nViewSonic's VA2703-LED is a 27\" widescreen LED display featuring Full HD 1080p resolution for a crisp, full-motion video experience. Exclusive ClearMotiv II imaging technology and high 10,000,000 : 1 dynamic contrast ratio make images smooth and colors vibrant. With a 16:9 aspect ratio, the display's large viewing area greatly enhances productivity when working on large spreadsheets or using multiple applications. The environmentally friendly VA2703-LED saves energy and money through ECO Mode, which reduces power consumption and extends backlight life. VA2703-LED provides great value and is an excellent visual solution for homes and businesses.\nProduct Type:\nLCD Monitor Technical Information\nNumber of Screens:\n1\nScreen Size:\n27\"\nScreen Mode:\nFull HD\nScreen Surface:\nAnti-glare\nResponse Time:\n3 ms\nAspect Ratio:\n16:9\nHorizontal Viewing Angle:\n170\u00c2\u00b0\nVertical Viewing Angle:\n160\u00c2\u00b0\nAdjustable Display Angle:\nYes\nBacklight Technology:\nLED\nFeatures:\nEco Saving Video\nMaximum Resolution:\n1920 x 1080\nContrast Ratio:\n1,200:1\nBrightness:\n300 Nit Interfaces/Ports\nDVI:\nYes\nVGA:\nYes Power Description\nOperating Power Consumption:\n30 W Physical Characteristics\nVESA Mount Compatible:\nYes\nVESA Mount Standard:\n100 x 100\nColor:\nBlack\nHeight:\n15.4\"\nWidth:\n25.4\"\nDepth:\n2.2\"\nHeight with Stand:\n17.17\"\nWidth with Stand:\n25.35\"\nDepth with Stand:\n6.84\"\nWeight (Approximate):\n10.63 lb\nWeight with Stand (Approximate):\n11.73 lb Shipping Information\nShipping Dimensions :\n20.5\" Height x 6.25\" Width x 28.75\" Depth\nCase Pack Qty :\n1\nShipping Weight :\n15.6 lb\nMiscellaneous\nPlatform Supported:\nPC\nMac",
    "main features": "Manufacturer/Supplier: Viewsonic Corporation\nManufacturer Part Number: VA2703-LED\nManufacturer Website Address: www.viewsonic.com\nBrand Name: Viewsonic\nProduct Series: VA\nProduct Model: VA2703-LED\nProduct Name: VA2703-LED Widescreen LCD Monitor\nMarketing Information: ViewSonic's VA2703-LED is a 27\" widescreen LED display featuring Full HD 1080p resolution for a crisp, full-motion video experience. Exclusive ClearMotiv II imaging technology and high 10,000,000 : 1 dynamic contrast ratio make images smooth and colors vibrant. With a 16:9 aspect ratio, the display's large viewing area greatly enhances productivity when working on large spreadsheets or using multiple applications. The environmentally friendly VA2703-LED saves energy and money through ECO Mode, which reduces power consumption and extends backlight life. VA2703-LED provides great value and is an excellent visual solution for homes and businesses.\nProduct Type: LCD Monitor\nNumber of Screens: 1\nScreen Size: 27\"\nScreen Mode: Full HD\nResponse Time: 3 ms\nAspect Ratio: 16:9\nHorizontal Viewing Angle: 170\u00c2\u00b0\nVertical Viewing Angle: 160\u00c2\u00b0\nAdjustable Display Angle: Yes\nBacklight Technology: LED\nFeatures: Eco Saving\nMaximum Resolution: 1920 x 1080\nContrast Ratio: 1,200:1\nBrightness: 300 Nit\nDVI: Yes\nVGA: Yes\nOperating Power Consumption: 30 W\nVESA Mount Compatible: Yes\nVESA Mount Standard: 100 x 100\nColor: Black\nHeight: 15.4\"\nWidth: 25.4\"\nDepth: 2.2\"\nHeight with Stand: 17.17\"\nWidth with Stand: 25.35\"\nDepth with Stand: 6.84\"\nWeight (Approximate): 10.63 lb\nWeight with Stand (Approximate): 11.73 lb\nPlatform Supported: PC, Mac\nGeneral Information\nManufacturer/Supplier:\nViewsonic Corporation\nManufacturer Part Number:\nVA2703-LED\nManufacturer Website Address:\nwww.viewsonic.com\nBrand Name:\nViewsonic\nProduct Series:\nVA\nProduct Model:\nVA2703-LED\nProduct Name:\nVA2703-LED Widescreen LCD Monitor\nMarketing Information:\nViewSonic's VA2703-LED is a 27\" widescreen LED display featuring Full HD 1080p resolution for a crisp, full-motion video experience. Exclusive ClearMotiv II imaging technology and high 10,000,000 : 1 dynamic contrast ratio make images smooth and colors vibrant. With a 16:9 aspect ratio, the display's large viewing area greatly enhances productivity when working on large spreadsheets or using multiple applications. The environmentally friendly VA2703-LED saves energy and money through ECO Mode, which reduces power consumption and extends backlight life. VA2703-LED provides great value and is an excellent visual solution for homes and businesses.\nProduct Type:\nLCD Monitor\nTechnical Information\nNumber of Screens:\n1\nScreen Size:\n27\"\nScreen Mode:\nFull HD\nScreen Surface:\nAnti-glare\nResponse Time:\n3 ms\nAspect Ratio:\n16:9\nHorizontal Viewing Angle:\n170\u00c2\u00b0\nVertical Viewing Angle:\n160\u00c2\u00b0\nAdjustable Display Angle:\nYes\nBacklight Technology:\nLED\nFeatures:\nEco Saving\nVideo\nMaximum Resolution:\n1920 x 1080\nContrast Ratio:\n1,200:1\nBrightness:\n300 Nit\nInterfaces/Ports\nDVI:\nYes\nVGA:\nYes\nPower Description\nOperating Power Consumption:\n30 W\nPhysical Characteristics\nVESA Mount Compatible:\nYes\nVESA Mount Standard:\n100 x 100\nColor:\nBlack\nHeight:\n15.4\"\nWidth:\n25.4\"\nDepth:\n2.2\"\nHeight with Stand:\n17.17\"\nWidth with Stand:\n25.35\"\nDepth with Stand:\n6.84\"\nWeight (Approximate):\n10.63 lb\nWeight with Stand (Approximate):\n11.73 lb\nShipping Information\nShipping Dimensions :\n20.5\" Height x 6.25\" Width x 28.75\" Depth\nCase Pack Qty :\n1\nShipping Weight :\n15.6 lb\nMiscellaneous\nPlatform Supported:\nPC\nMac",
    "manufacturer part number": "VA2703-LED",
    "manufacturer website address": "www.viewsonic.com",
    "manufacturersupplier": "Viewsonic Corporation",
    "marketing information": "ViewSonic's VA2703-LED is a 27\" widescreen LED display featuring Full HD 1080p resolution for a crisp, full-motion video experience. Exclusive ClearMotiv II imaging technology and high 10,000,000 : 1 dynamic contrast ratio make images smooth and colors vibrant. With a 16:9 aspect ratio, the display's large viewing area greatly enhances productivity when working on large spreadsheets or using multiple applications. The environmentally friendly VA2703-LED saves energy and money through ECO Mode, which reduces power consumption and extends backlight life. VA2703-LED provides great value and is an excellent visual solution for homes and businesses.",
    "product model": "VA2703-LED",
    "product name": "VA2703-LED Widescreen LCD Monitor",
    "product series": "VA",
    "product type": "LCD Monitor"
}