{
    "<page title>": "Viewsonic VX2370SMH LED 23\" LED LCD Monitor 4 MS HDMI DVI VGA 7MS Tilt 766907659115 | eBay",
    "brand name": "Viewsonic",
    "certifications  standards": "CE, CB, BSMI, SASO, C-tick, UL/cUL, FCC-B, ICES003, TUV-S, UL CoC, GOSTR/Hygienic, UkrSEPRO, CCC",
    "main features": "Manufacturer/Supplier: Viewsonic Corporation\nManufacturer Part Number: VX2370SMH-LED\nManufacturer Website Address: www.viewsonic.com\nBrand Name: Viewsonic\nProduct Series: X\nProduct Model: VX2370Smh-LED\nProduct Name: VX2370Smh-LED Widescreen LCD Monitor\nMarketing Information: Designed with frameless bezel and touch keys, the ViewSonic VX2370Smh-LED sets a new milestone for display design delivering cutting- edge, trendy ambience into any living space or office. Through the remarkable image quality of Full HD 1080p, 30,000,000:1 dynamic contrast ratio, and up to 4ms response time, combined with SuperClear\u00e2\u0084\u00a2 IPS, the VX2370Smh-LED brings vivid and sharp images to life with no limited viewing angles. An HDMI port provides high resolution image/video connection with devices for gaming, graphics, and HD entertainment. A pair of speakers powered by SRS Premium Sound\u00c2\u00ae delivers true-tonature high-end stereo, complementing the refined display perfectly for a wide variety of applications.\nProduct Type: LCD Monitor\nNumber of Screens: 1\nScreen Size: 23\"\nScreen Mode: Full HD\nResponse Time: 4 ms\nHorizontal Viewing Angle: 178\u00c2\u00b0\nVertical Viewing Angle: 178\u00c2\u00b0\nAdjustable Display Angle: Yes\nBacklight Technology: LED\nFeatures: In-plane Switching (IPS) Technology, Touch Controls\nMaximum Resolution: 1920 x 1080\nStandard Refresh Rate: 76 Hz\nContrast Ratio: 1,000:1\nBrightness: 250 Nit\nSpeakers: Yes\nDVI: Yes\nHDMI: Yes\nVGA: Yes\nBuilt-in Devices: Speaker\nInput Voltage: 110 V AC, 220 V AC\nOperating Power Consumption: 27 W\nHeight with Stand: 16.10\"\nWidth with Stand: 21\"\nDepth with Stand: 7.07\"\nWeight with Stand (Approximate): 8.60 lb\nCertifications & Standards:\nCE, CB, BSMI, SASO, C-tick, UL/cUL, FCC-B, ICES003, TUV-S, UL CoC, GOSTR/Hygienic, UkrSEPRO, CCC\nPlatform Supported: PC, Mac\nGreen Compliant: Yes\nGreen Compliance Certificate/Authority: TCO Certified Displays 5.2, ErP, Energy Star, EPEAT Silver, WEEE, RoHS General Information\nManufacturer/Supplier:\nViewsonic Corporation\nManufacturer Part Number:\nVX2370SMH-LED\nManufacturer Website Address:\nwww.viewsonic.com\nBrand Name:\nViewsonic\nProduct Series:\nX\nProduct Model:\nVX2370Smh-LED\nProduct Name:\nVX2370Smh-LED Widescreen LCD Monitor\nMarketing Information:\nDesigned with frameless bezel and touch keys, the ViewSonic VX2370Smh-LED sets a new milestone for display design delivering cutting- edge, trendy ambience into any living space or office. Through the remarkable image quality of Full HD 1080p, 30,000,000:1 dynamic contrast ratio, and up to 4ms response time, combined with SuperClear\u00e2\u0084\u00a2 IPS, the VX2370Smh-LED brings vivid and sharp images to life with no limited viewing angles. An HDMI port provides high resolution image/video connection with devices for gaming, graphics, and HD entertainment. A pair of speakers powered by SRS Premium Sound\u00c2\u00ae delivers true-tonature high-end stereo, complementing the refined display perfectly for a wide variety of applications.\nProduct Type:\nLCD Monitor Technical Information\nNumber of Screens:\n1\nScreen Size:\n23\"\nScreen Mode:\nFull HD\nScreen Surface:\nAnti-glare\nResponse Time:\n4 ms\nHorizontal Viewing Angle:\n178\u00c2\u00b0\nVertical Viewing Angle:\n178\u00c2\u00b0\nAdjustable Display Angle:\nYes\nBacklight Technology:\nLED\nFeatures:\nIn-plane Switching (IPS) Technology\nTouch Controls Video\nMaximum Resolution:\n1920 x 1080\nStandard Refresh Rate:\n76 Hz\nContrast Ratio:\n1,000:1\nBrightness:\n250 Nit Audio\nNumber of Speakers:\n2\nSpeakers:\nYes Interfaces/Ports\nDVI:\nYes\nHDMI:\nYes\nVGA:\nYes Built-in Devices\nBuilt-in Devices:\nSpeaker Power Description\nInput Voltage:\n110 V AC\n220 V AC\nOperating Power Consumption:\n27 W Physical Characteristics\nHeight with Stand:\n16.10\"\nWidth with Stand:\n21\"\nDepth with Stand:\n7.07\"\nWeight with Stand (Approximate):\n8.60 lb Shipping Information\nShipping Dimensions :\n7.5\" Height x 19.0\" Width x 23.0\" Depth\nCase Pack Qty :\n1\nShipping Weight :\n20.0 lb\nMiscellaneous\nCertifications & Standards:\nCE\nCB\nBSMI\nSASO\nC-tick\nUL/cUL\nFCC-B\nICES003\nTUV-S\nUL CoC\nGOSTR/Hygienic\nUkrSEPRO\nCCC\nPlatform Supported:\nPC\nMac\nGreen Compliant:\nYes\nGreen Compliance Certificate/Authority:\nTCO Certified Displays 5.2\nErP\nEnergy Star\nEPEAT Silver\nWEEE\nRoHS",
    "manufacturer part number": "VX2370SMH-LED",
    "manufacturer website address": "www.viewsonic.com",
    "manufacturersupplier": "Viewsonic Corporation",
    "marketing information": "Designed with frameless bezel and touch keys, the ViewSonic VX2370Smh-LED sets a new milestone for display design delivering cutting- edge, trendy ambience into any living space or office. Through the remarkable image quality of Full HD 1080p, 30,000,000:1 dynamic contrast ratio, and up to 4ms response time, combined with SuperClear\u00e2\u0084\u00a2 IPS, the VX2370Smh-LED brings vivid and sharp images to life with no limited viewing angles. An HDMI port provides high resolution image/video connection with devices for gaming, graphics, and HD entertainment. A pair of speakers powered by SRS Premium Sound\u00c2\u00ae delivers true-tonature high-end stereo, complementing the refined display perfectly for a wide variety of applications.",
    "product model": "VX2370Smh-LED",
    "product name": "VX2370Smh-LED Widescreen LCD Monitor",
    "product series": "X",
    "product type": "LCD Monitor"
}