{
    "<page title>": "Acer H276HL 27\" LED LCD Monitor 16 9 5 MS Adjustable Display Angle UM HH6AA 001 | eBay",
    "adjustable display angle": [
        "Yes",
        "Yes"
    ],
    "adjustable display height": [
        "No",
        "No"
    ],
    "adjustable display pivot": [
        "No",
        "No"
    ],
    "aspect ratio": [
        "16:9",
        "16:9",
        "16:9",
        "16:9",
        "16:9",
        "16:9",
        "16:9",
        "16:9"
    ],
    "backlight technology": [
        "LED",
        "LED",
        "LED",
        "LED"
    ],
    "brand name": [
        "Acer",
        "Acer"
    ],
    "brightness": [
        "250 Nit",
        "250 Nit",
        "250 Nit",
        "250 Nit",
        "250 Nit",
        "250 Nit",
        "250 Nit",
        "250 Nit",
        "250 Nit"
    ],
    "color": "Black",
    "color supported": [
        "16.7 Million Colors",
        "16.7 Million Colors",
        "16.7 Million Colors",
        "16.7 Million Colors",
        "16.7 Million Colors",
        "16.7 Million Colors",
        "16.7 Million Colors"
    ],
    "contrast ratio": [
        "100,000,000:1",
        "100,000,000:1",
        "100,000,000:1",
        "100,000,000:1",
        "100,000,000:1",
        "100,000,000:1",
        "100,000,000:1",
        "100,000,000:1"
    ],
    "dvi": "Yes",
    "features": [
        "CrystalBrite\nAudio\nSpeakers:\nYes\nBuilt-in Devices\nSpeakers:\nYes\nCamera\nScreen Size:\n27\"\nDisplay & Graphics\nAspect Ratio:\n16:9\nBacklight Technology:\nLED\nBrightness:\n250 Nit\nColor Supported:\n16.7 Million Colors\nContrast Ratio:\n100,000,000:1\nHorizontal Viewing Angle:\n178\u00c2\u00b0\nMaximum Resolution:\n1920 x 1080\nResponse Time:\n5 ms\nScreen Mode:\nFull HD\nScreen Size:\n27\"\nVertical Viewing Angle:\n178\u00c2\u00b0\nGeneral Information\nBrand Name:\nAcer\nManufacturer Part Number:\nUM.HH6AA.001\nManufacturer Website Address:\nhttp://us.acer.com\nManufacturer/Supplier:\nAcer, Inc\nPackage Contents:\nH276HL Widescreen LCD Monitor1 x DVI Cable1 x HDMI Cable1 x VGA CablePower Cord\nProduct Model:\nH276HL\nProduct Name:\nH276HL Widescreen LCD Monitor\nProduct Series:\nH\nProduct Type:\nLCD Monitor\nImage\nAspect Ratio:\n16:9\nBrightness:\n250 Nit\nColor Supported:\n16.7 Million Colors\nContrast Ratio:\n100,000,000:1\nMaximum Resolution:\n1920 x 1080\nInterfaces/Ports\nDVI:\nYes\nHDMI:\nYes\nVGA:\nYes\nMiscellaneous\nFeatures:\nCrystalBrite\nGreen Compliance Certificate/Authority:\nENERGY STAR\nGreen Compliance Certificate/Authority:\nMPR II\nGreen Compliant:\nYes\nPackage Contents:\nH276HL Widescreen LCD Monitor1 x DVI Cable1 x HDMI Cable1 x VGA CablePower Cord\nPhysical Characteristics\nColor:\nBlack\nPower Description\nInput Voltage:\n110 V AC\nInput Voltage:\n220 V AC\nOff-Mode Power Consumption:\n400 mW\nOperating Power Consumption:\n29.03 W\nStandby Power Consumption:\n450 mW\nProduct Information\nBrightness:\n250 Nit\nColor Supported:\n16.7 Million Colors\nFeatures:\nCrystalBrite\nStorage\nFeatures:\nCrystalBrite\nTechnical Information\nAdjustable Display Angle:\nYes\nAdjustable Display Height:\nNo\nAdjustable Display Pivot:\nNo\nAspect Ratio:\n16:9\nBacklight Technology:\nLED\nBrightness:\n250 Nit\nContrast Ratio:\n100,000,000:1\nFeatures:\nCrystalBrite\nHorizontal Viewing Angle:\n178\u00c2\u00b0\nInput Voltage:\n110 V AC\nInput Voltage:\n220 V AC\nMaximum Resolution:\n1920 x 1080\nNumber of Screens:\n1\nPanel Technology:\nIn-plane Switching (IPS) Technology\nResponse Time:\n5 ms\nScreen Mode:\nFull HD\nScreen Size:\n27\"\nSpeakers:\nYes\nVertical Viewing Angle:\n178\u00c2\u00b0\nVideo\nAspect Ratio:\n16:9\nBrightness:\n250 Nit\nColor Supported:\n16.7 Million Colors\nContrast Ratio:\n100,000,000:1\nMaximum Resolution:\n1920 x 1080\nScreen Mode:\nFull HD\nStandard Refresh Rate:\n60 Hz\nWireless Specifications\nFeatures:\nCrystalBrite",
        "CrystalBrite",
        "CrystalBrite",
        "CrystalBrite",
        "CrystalBrite",
        "CrystalBrite",
        "CrystalBrite"
    ],
    "green compliance certificateauthority": [
        "MPR II",
        "ENERGY STAR"
    ],
    "green compliant": "Yes",
    "hdmi": "Yes",
    "horizontal viewing angle": [
        "178\u00c2\u00b0",
        "178\u00c2\u00b0",
        "178\u00c2\u00b0",
        "178\u00c2\u00b0"
    ],
    "input voltage": [
        "220 V AC",
        "110 V AC",
        "110 V AC",
        "220 V AC",
        "220 V AC",
        "110 V AC"
    ],
    "manufacturer part number": [
        "UM.HH6AA.001",
        "UM.HH6AA.001"
    ],
    "manufacturer website address": [
        "http://us.acer.com",
        "http://us.acer.com"
    ],
    "manufacturersupplier": [
        "Acer, Inc",
        "Acer, Inc"
    ],
    "maximum resolution": [
        "1920 x 1080",
        "1920 x 1080",
        "1920 x 1080",
        "1920 x 1080",
        "1920 x 1080",
        "1920 x 1080",
        "1920 x 1080",
        "1920 x 1080"
    ],
    "number of screens": [
        "1",
        "1"
    ],
    "offmode power consumption": "400 mW",
    "operating power consumption": "29.03 W",
    "package contents": [
        "H276HL Widescreen LCD Monitor1 x DVI Cable1 x HDMI Cable1 x VGA CablePower Cord",
        "H276HL Widescreen LCD Monitor1 x DVI Cable1 x HDMI Cable1 x VGA CablePower Cord",
        "H276HL Widescreen LCD Monitor1 x DVI Cable1 x HDMI Cable1 x VGA CablePower Cord"
    ],
    "panel technology": [
        "In-plane Switching (IPS) Technology",
        "In-plane Switching (IPS) Technology"
    ],
    "product model": [
        "H276HL",
        "H276HL"
    ],
    "product name": [
        "H276HL Widescreen LCD Monitor",
        "H276HL Widescreen LCD Monitor"
    ],
    "product series": [
        "H",
        "H"
    ],
    "product type": [
        "LCD Monitor",
        "LCD Monitor"
    ],
    "response time": [
        "5 ms",
        "5 ms",
        "5 ms",
        "5 ms"
    ],
    "screen mode": [
        "Full HD",
        "Full HD",
        "Full HD",
        "Full HD",
        "Full HD",
        "Full HD"
    ],
    "screen size": [
        "27\"",
        "27\"",
        "27\"",
        "27\"",
        "27\""
    ],
    "speakers": [
        "Yes",
        "Yes",
        "Yes",
        "Yes"
    ],
    "standard refresh rate": [
        "60 Hz",
        "60 Hz"
    ],
    "standby power consumption": "450 mW",
    "vertical viewing angle": [
        "178\u00c2\u00b0",
        "178\u00c2\u00b0",
        "178\u00c2\u00b0",
        "178\u00c2\u00b0"
    ],
    "vga": "Yes"
}