{
    "<page title>": "Viewsonic VA2232WM LED 22\" LED LCD Monitor 16 10 5 MS 1680x1050 VGA DVI 5ms 766907403329 | eBay",
    "brand name": "Viewsonic",
    "certifications  standards": "CE , CB , UL , cUL , FCC-B / ICES-003B , UL-AR/TUV-S , NOM , Nemko ERGO , GS , GOST-R+Hygienic , UkrSEPRO , CCC , CEL level 1 BSMI , PSB , C-tick , SASO",
    "general information": "Manufacturer/Supplier:\nViewsonic Corporation\nManufacturer Part Number:\nVA2232WM-LED\nManufacturer Website Address:\nwww.viewsonic.com\nBrand Name:\nViewsonic\nProduct Series:\nVA\nProduct Model:\nVA2232WM-LED\nProduct Name:\n22\" LED Display\nMarketing Information:\nViewSonic's 22-inch VA2232wm-LED displays are new members of the VA series; with a native 1680 x 1050 resolution and sRGB color calibration function, the two models present exquisite picture quality and an immersive viewing experience. Along with an impressive 10,000,000:1 dynamic contrast ratio, the VA2232wm-LED automatically detect and adjust dark and bright levels to greatly enhance grayscale and color contrast performance. Save energy and money with ViewSonic's ECO Mode solution which reduces power consumption and extends backlight life. The VA2232wm-LED provide great value concerning viewing performance and are excellent solutions for home and business.\nProduct Type:\nLCD Monitor Technical Information\nNumber of Screens:\n1\nScreen Size:\n22\"\nScreen Mode:\nWSXGA+\nScreen Surface:\nAnti-glare\nResponse Time:\n5 ms\nAspect Ratio:\n16:10\nHorizontal Viewing Angle:\n170\u00c2\u00b0\nVertical Viewing Angle:\n160\u00c2\u00b0\nBacklight Technology:\nLED Video\nMaximum Resolution:\n1680 x 1050\nStandard Refresh Rate:\n75 Hz\nContrast Ratio:\n1,000:1\nBrightness:\n250 Nit Audio\nNumber of Speakers:\n2\nSpeakers:\nYes Interfaces/Ports\nDVI:\nYes\nVGA:\nYes Power Description\nInput Voltage:\n110 V AC\n220 V AC Physical Characteristics\nVESA Mount Compatible:\nYes\nVESA Mount Standard:\n100 x 100\nHeight:\n13.9\"\nWidth:\n20.0\"\nDepth:\n2.4\"\nHeight with Stand:\n16.39\"\nWidth with Stand:\n20.11\"\nDepth with Stand:\n7.69\"\nWeight (Approximate):\n7.67 lb\nWeight with Stand (Approximate):\n8.62 lb Shipping Information\nShipping Dimensions :\n5.7\" Height x 19.5\" Width x 22.2\" Depth\nShipping Weight :\n11.65 lb\nMiscellaneous\nCertifications & Standards:\nCE\nCB\nUL\ncUL\nFCC-B / ICES-003B\nUL-AR/TUV-S\nNOM\nNemko ERGO\nGS\nGOST-R+Hygienic\nUkrSEPRO\nCCC\nCEL level 1 BSMI\nPSB\nC-tick\nSASO\nPlatform Supported:\nPC\nMac\nGreen Compliant:\nYes\nGreen Compliance Certificate/Authority:\nWEEE\nRoHS\nREACH\nErP",
    "main features": "Manufacturer/Supplier: Viewsonic Corporation\nManufacturer Part Number: VA2232WM-LED\nManufacturer Website Address: www.viewsonic.com\nBrand Name: Viewsonic\nProduct Series: VA\nProduct Model: VA2232WM-LED\nProduct Name: 22\" LED Display\nMarketing Information: ViewSonic's 22-inch VA2232wm-LED displays are new members of the VA series; with a native 1680 x 1050 resolution and sRGB color calibration function, the two models present exquisite picture quality and an immersive viewing experience. Along with an impressive 10,000,000:1 dynamic contrast ratio, the VA2232wm-LED automatically detect and adjust dark and bright levels to greatly enhance grayscale and color contrast performance. Save energy and money with ViewSonic's ECO Mode solution which reduces power consumption and extends backlight life. The VA2232wm-LED provide great value concerning viewing performance and are excellent solutions for home and business.\nProduct Type: LCD Monitor\nNumber of Screens: 1\nScreen Size: 22\"\nScreen Mode: WSXGA+\nResponse Time: 5 ms\nAspect Ratio: 16:10\nHorizontal Viewing Angle: 170\u00c2\u00b0\nVertical Viewing Angle: 160\u00c2\u00b0\nBacklight Technology: LED\nMaximum Resolution: 1680 x 1050\nStandard Refresh Rate: 75 Hz\nContrast Ratio: 1,000:1\nBrightness: 250 Nit\nSpeakers: Yes\nDVI: Yes\nVGA: Yes\nInput Voltage: 110 V AC, 220 V AC\nVESA Mount Compatible: Yes\nVESA Mount Standard: 100 x 100\nHeight: 13.9\"\nWidth: 20.0\"\nDepth: 2.4\"\nHeight with Stand: 16.39\"\nWidth with Stand: 20.11\"\nDepth with Stand: 7.69\"\nWeight (Approximate): 7.67 lb\nWeight with Stand (Approximate): 8.62 lb\nCertifications & Standards:\nCE , CB , UL , cUL , FCC-B / ICES-003B , UL-AR/TUV-S , NOM , Nemko ERGO , GS , GOST-R+Hygienic , UkrSEPRO , CCC , CEL level 1 BSMI , PSB , C-tick , SASO\nPlatform Supported: PC, Mac\nGreen Compliant: Yes\nGreen Compliance Certificate/Authority: WEEE, RoHS, REACH, ErP\nGeneral Information\nManufacturer/Supplier:\nViewsonic Corporation\nManufacturer Part Number:\nVA2232WM-LED\nManufacturer Website Address:\nwww.viewsonic.com\nBrand Name:\nViewsonic\nProduct Series:\nVA\nProduct Model:\nVA2232WM-LED\nProduct Name:\n22\" LED Display\nMarketing Information:\nViewSonic's 22-inch VA2232wm-LED displays are new members of the VA series; with a native 1680 x 1050 resolution and sRGB color calibration function, the two models present exquisite picture quality and an immersive viewing experience. Along with an impressive 10,000,000:1 dynamic contrast ratio, the VA2232wm-LED automatically detect and adjust dark and bright levels to greatly enhance grayscale and color contrast performance. Save energy and money with ViewSonic's ECO Mode solution which reduces power consumption and extends backlight life. The VA2232wm-LED provide great value concerning viewing performance and are excellent solutions for home and business.\nProduct Type:\nLCD Monitor\nTechnical Information\nNumber of Screens:\n1\nScreen Size:\n22\"\nScreen Mode:\nWSXGA+\nScreen Surface:\nAnti-glare\nResponse Time:\n5 ms\nAspect Ratio:\n16:10\nHorizontal Viewing Angle:\n170\u00c2\u00b0\nVertical Viewing Angle:\n160\u00c2\u00b0\nBacklight Technology:\nLED\nVideo\nMaximum Resolution:\n1680 x 1050\nStandard Refresh Rate:\n75 Hz\nContrast Ratio:\n1,000:1\nBrightness:\n250 Nit\nAudio\nNumber of Speakers:\n2\nSpeakers:\nYes\nInterfaces/Ports\nDVI:\nYes\nVGA:\nYes\nPower Description\nInput Voltage:\n110 V AC\n220 V AC\nPhysical Characteristics\nVESA Mount Compatible:\nYes\nVESA Mount Standard:\n100 x 100\nHeight:\n13.9\"\nWidth:\n20.0\"\nDepth:\n2.4\"\nHeight with Stand:\n16.39\"\nWidth with Stand:\n20.11\"\nDepth with Stand:\n7.69\"\nWeight (Approximate):\n7.67 lb\nWeight with Stand (Approximate):\n8.62 lb\nShipping Information\nShipping Dimensions :\n5.7\" Height x 19.5\" Width x 22.2\" Depth\nShipping Weight :\n11.65 lb\nMiscellaneous\nCertifications & Standards:\nCE\nCB\nUL\ncUL\nFCC-B / ICES-003B\nUL-AR/TUV-S\nNOM\nNemko ERGO\nGS\nGOST-R+Hygienic\nUkrSEPRO\nCCC\nCEL level 1 BSMI\nPSB\nC-tick\nSASO\nPlatform Supported:\nPC\nMac\nGreen Compliant:\nYes\nGreen Compliance Certificate/Authority:\nWEEE\nRoHS\nREACH\nErP",
    "manufacturer part number": "VA2232WM-LED",
    "manufacturer website address": "www.viewsonic.com",
    "manufacturersupplier": "Viewsonic Corporation",
    "marketing information": "ViewSonic's 22-inch VA2232wm-LED displays are new members of the VA series; with a native 1680 x 1050 resolution and sRGB color calibration function, the two models present exquisite picture quality and an immersive viewing experience. Along with an impressive 10,000,000:1 dynamic contrast ratio, the VA2232wm-LED automatically detect and adjust dark and bright levels to greatly enhance grayscale and color contrast performance. Save energy and money with ViewSonic's ECO Mode solution which reduces power consumption and extends backlight life. The VA2232wm-LED provide great value concerning viewing performance and are excellent solutions for home and business.",
    "product model": "VA2232WM-LED",
    "product name": "22\" LED Display",
    "product series": "VA",
    "product type": "LCD Monitor"
}