{
    "<page title>": "Viewsonic 27in LED LCD Monitor 16 9 3 MS VX2703MH LED 1920x1080 1200 1 1080p 766907647716 | eBay",
    "brand name": "Viewsonic",
    "certifications  standards": "CE , CB , BSMI , PSB , SASO , C-tick , E-Standby , KC , UL/cUL , FCC-B (including ICES003) , UL CoC , Mexico Energy , GOST-R/Hygienic , UkrSEPRO , CCC , China Energy , SVHC",
    "main features": "Standard Warranty: 3 Year Limited\nManufacturer/Supplier: Viewsonic Corporation\nManufacturer Part Number: VX2703MH-LED\nManufacturer Website Address: www.viewsonic.com\nBrand Name: Viewsonic\nProduct Series: VX\nProduct Model: VX2703mh-LED\nProduct Name: 27\" Widescreen LED with Full 1080p Resolution Versatile Monitor That Performs\nMarketing Information: ViewSonic's VX2703mh-LED features a 27\" widescreen LED panel monitor with up to 40%* energy saving compared to a regular 27\" monitor. Environmentally friendly mercury free VX2703mh-LED offers Full HD 1920x1080 resolution, HDMI and DVI inputs with HDCP, integrated power, 3ms response time, 10,000,000:1 MEGA Dynamic Contrast Ratio, and built-in speakers with SRS Premium Sound. Ideal for both home and office with a contemporary thin bezel design. The aspect ratio adjustment feature automatically senses the input single and will not stretch a 4:3 signal, but instead will position the image in the middle of the screen with side bars. A 3-year limited warranty, the industry's best pixel performance policy, energy saving Eco mode and Windows 7 certification make VX2703mh-LED a great long term investment.\nProduct Type: LCD Monitor\nNumber of Screens: 1\nScreen Size: 27\"\nScreen Mode: Full HD\nResponse Time: 3 ms\nAspect Ratio: 16:9\nHorizontal Viewing Angle: 170\u00c2\u00b0\nVertical Viewing Angle: 160\u00c2\u00b0\nAdjustable Display Angle: Yes\nBacklight Technology: LED\nHDCP Supported: Yes\nMaximum Resolution: 1920 x 1080\nContrast Ratio: 1,200:1\nBrightness: 300 Nit\nSpeakers: Yes\nDVI: Yes\nHDMI: Yes\nVGA: Yes\nBuilt-in Devices: Speaker\nInput Voltage: 110 V AC, 220 V AC\nOperating Power Consumption: 39 W\nColor: Black\nHeight: 15.4\"\nWidth: 25.4\"\nDepth: 2.2\"\nHeight with Stand: 17.20\"\nWidth with Stand: 25.40\"\nDepth with Stand: 6.90\"\nWeight (Approximate): 10.80 lb\nWeight with Stand (Approximate): 11.90 lb\nPackage Contents:\n27\" Widescreen LED with Full 1080p Resolution Versatile Monitor That Performs , Power Cable , Audio Cable , VGA Cable , DVI Cable , User Guide , Quick Start Guide , ViewSonic Wizard CD-ROM\nCertifications & Standards:\nCE , CB , BSMI , PSB , SASO , C-tick , E-Standby , KC , UL/cUL , FCC-B (including ICES003) , UL CoC , Mexico Energy , GOST-R/Hygienic , UkrSEPRO , CCC , China Energy , SVHC\nPlatform Supported: PC, Mac\nGreen Compliant: Yes\nGreen Compliance Certificate/Authority: Energy Star, ErP, EPEAT Silver, WEEE, RoHS General Information\nManufacturer/Supplier:\nViewsonic Corporation\nManufacturer Part Number:\nVX2703MH-LED\nManufacturer Website Address:\nwww.viewsonic.com\nBrand Name:\nViewsonic\nProduct Series:\nVX\nProduct Model:\nVX2703mh-LED\nProduct Name:\n27\" Widescreen LED with Full 1080p Resolution Versatile Monitor That Performs\nMarketing Information:\nViewSonic's VX2703mh-LED features a 27\" widescreen LED panel monitor with up to 40%* energy saving compared to a regular 27\" monitor. Environmentally friendly mercury free VX2703mh-LED offers Full HD 1920x1080 resolution, HDMI and DVI inputs with HDCP, integrated power, 3ms response time, 10,000,000:1 MEGA Dynamic Contrast Ratio, and built-in speakers with SRS Premium Sound. Ideal for both home and office with a contemporary thin bezel design. The aspect ratio adjustment feature automatically senses the input single and will not stretch a 4:3 signal, but instead will position the image in the middle of the screen with side bars. A 3-year limited warranty, the industry's best pixel performance policy, energy saving Eco mode and Windows 7 certification make VX2703mh-LED a great long term investment.\nProduct Type:\nLCD Monitor Technical Information\nNumber of Screens:\n1\nScreen Size:\n27\"\nScreen Mode:\nFull HD\nScreen Surface:\nAnti-glare\nResponse Time:\n3 ms\nAspect Ratio:\n16:9\nHorizontal Viewing Angle:\n170\u00c2\u00b0\nVertical Viewing Angle:\n160\u00c2\u00b0\nAdjustable Display Angle:\nYes\nBacklight Technology:\nLED\nHDCP Supported:\nYes\nFeatures:\nAuto-off\nClearMotiv II Video\nMaximum Resolution:\n1920 x 1080\nContrast Ratio:\n1,200:1\nBrightness:\n300 Nit Audio\nSpeakers:\nYes Interfaces/Ports\nDVI:\nYes\nHDMI:\nYes\nVGA:\nYes\nHeadphone:\nYes Built-in Devices\nBuilt-in Devices:\nSpeaker Power Description\nInput Voltage:\n110 V AC\n220 V AC\nOperating Power Consumption:\n39 W Physical Characteristics\nColor:\nBlack\nHeight:\n15.4\"\nWidth:\n25.4\"\nDepth:\n2.2\"\nHeight with Stand:\n17.20\"\nWidth with Stand:\n25.40\"\nDepth with Stand:\n6.90\"\nWeight (Approximate):\n10.80 lb\nWeight with Stand (Approximate):\n11.90 lb Shipping Information\nShipping Dimensions :\n6.38\" Height x 20.5\" Width x 28.75\" Depth\n:\nShipping Weight :\n17.15 lb\n:\nMiscellaneous\nPackage Contents:\n27\" Widescreen LED with Full 1080p Resolution Versatile Monitor That Performs\nPower Cable\nAudio Cable\nVGA Cable\nDVI Cable\nUser Guide\nQuick Start Guide\nViewSonic Wizard CD-ROM\nCertifications & Standards:\nCE\nCB\nBSMI\nPSB\nSASO\nC-tick\nE-Standby\nKC\nUL/cUL\nFCC-B (including ICES003)\nUL CoC\nMexico Energy\nGOST-R/Hygienic\nUkrSEPRO\nCCC\nChina Energy\nSVHC\nPlatform Supported:\nPC\nMac\nGreen Compliant:\nYes\nGreen Compliance Certificate/Authority:\nEnergy Star\nErP\nEPEAT Silver\nWEEE\nRoHS Warranty\nStandard Warranty:\n3 Year Limited",
    "manufacturer part number": "VX2703MH-LED",
    "manufacturer website address": "www.viewsonic.com",
    "manufacturersupplier": "Viewsonic Corporation",
    "marketing information": "ViewSonic's VX2703mh-LED features a 27\" widescreen LED panel monitor with up to 40%* energy saving compared to a regular 27\" monitor. Environmentally friendly mercury free VX2703mh-LED offers Full HD 1920x1080 resolution, HDMI and DVI inputs with HDCP, integrated power, 3ms response time, 10,000,000:1 MEGA Dynamic Contrast Ratio, and built-in speakers with SRS Premium Sound. Ideal for both home and office with a contemporary thin bezel design. The aspect ratio adjustment feature automatically senses the input single and will not stretch a 4:3 signal, but instead will position the image in the middle of the screen with side bars. A 3-year limited warranty, the industry's best pixel performance policy, energy saving Eco mode and Windows 7 certification make VX2703mh-LED a great long term investment.",
    "package contents": "27\" Widescreen LED with Full 1080p Resolution Versatile Monitor That Performs , Power Cable , Audio Cable , VGA Cable , DVI Cable , User Guide , Quick Start Guide , ViewSonic Wizard CD-ROM",
    "product model": "VX2703mh-LED",
    "product name": "27\" Widescreen LED with Full 1080p Resolution Versatile Monitor That Performs",
    "product series": "VX",
    "product type": "LCD Monitor"
}