{
    "<page title>": "Genuine Dell ELO Entuitive E926109 15\" Touchscreen Monitor w Cables NX436 | eBay",
    "additional mpn": "E785333",
    "analog video input connector": "1 x 15 Pin D-Sub connector",
    "aspect ratio": "15\"",
    "audio input": "Line In (3.5mm)",
    "audio output": "Speaker(s)",
    "brand": "Dell",
    "color support": "16.2M Colors, 24-bit (16.7M Colors)",
    "contrast ratio": "400:1",
    "digital video input standard": "DVI-D, DVI-I",
    "display technology": "LED LCD",
    "form factor": "Desktop",
    "input device": "Keyboard, Magnetic Stripe Reader, Touch Screen",
    "item description": "We ship 99% of our orders the same day, and we offer express shipping for those that must have their replacement as soon as possible. At Red Planet we guarantee every product we sell and we stand behind our guarantee with live customer service!\nThis auction is for a USED Genuine Dell Elo Entuitive E926109 1529L 15\" Touchscreen Monitor With Cable Kit. Compatible Dell Part Numbers: ET1529L-8CWA-1-GY-G, E926109, NX436. DOES NOT INCLUDE STAND\nProduct Identifiers\nBrand\nElo\nModel\n1529L\nUPC\n0741149301275, 7411493010538\nAdditional MPN\nE785333\nKey Features\nProduct Line\nElo Touch\nDisplay Technology\nFlat Panel LCD TFT (Active Matrix), LCD\nScreen Size\n15\"\nMaximum Resolution\n1024 x 768\nAspect Ratio\n4:3\nContrast Ratio\n400:1\nResponse Time\n25 ms\nTechnical Features\nSynchronization Range - Vertical\n56 - 75 kHz\nSynchronization Range - Horizontal\n31 - 60 kHz\nMax Viewing Angle Horizontal\n120\u00c2\u00b0\nMax Viewing Angle Vertical\n100\u00c2\u00b0\nRegulatory Approval\nC-TICK, C-Tick, CE, EPA, Energy star, FCC, FCC Class A, RoHS, TUV GS, TUV-GS, UL, VCCI, cUL\nColor Support\n16.2M Colors, 24-bit (16.7M Colors)\nForm Factor\nDesktop\nConnectivity\nAudio Output\nSpeaker(s)\nAudio Input\nLine In (3.5mm)\nInput Device\nKeyboard, Magnetic Stripe Reader, Touch Screen\nAnalog Video Input Connector\n1 x 15 Pin D-Sub connector\nDigital Video Input Standard\nDVI-D, DVI-I\nMiscellaneous\nMonitor Color\nDark Gray\nMonitor Platform Source\nPC, PC, Mac",
    "max resolution": "1024 x 768",
    "max viewing angle horizontal": "120\u00c2\u00b0",
    "max viewing angle vertical": "100\u00c2\u00b0",
    "maximum resolution": "1024 x 768",
    "model": "1529L",
    "monitor color": "Dark Gray",
    "monitor platform source": "PC, PC, Mac",
    "mpn": "ET1529L-8CWA-1-GY-G, E926109, NX436",
    "product line": "Elo Touch",
    "regulatory approval": "C-TICK, C-Tick, CE, EPA, Energy star, FCC, FCC Class A, RoHS, TUV GS, TUV-GS, UL, VCCI, cUL",
    "response time": "25 ms",
    "screen size": "15\"",
    "synchronization range  horizontal": "31 - 60 kHz",
    "synchronization range  vertical": "56 - 75 kHz",
    "upc": "0741149301275, 7411493010538"
}