{
    "<page title>": "NEC Display MultiSync EA234WMI BK 23\" LED LCD Monitor 16 9 6 MS EA234WMI BK | eBay",
    "brand name": "NEC Display",
    "general information": "Manufacturer/Supplier:\nNEC Display Solutions\nManufacturer Part Number:\nEA234WMI-BK\nManufacturer Website Address:\nhttp://www.necdisplay.com\nBrand Name:\nNEC Display\nProduct Line:\nMultiSync\nProduct Series:\nEA\nProduct Model:\nEA234WMi-BK\nProduct Name:\n23\" Widescreen LED-Backlit Desktop Monitor w/ IPS LCD Panel\nMarketing Information:\nThe 23\" NEC MultiSync EA234WMi is an LED-backlit desktop monitor ideal for corporate environments. Designed to enhance work performance, this widescreen model features IPS panel technology with wide viewing angles and ergonomic adjustability. The LED backlighting of the EA234WMi allows for a slimmer profile, lighter weight and increased power savings compared to previous generation models. ControlSync\u00e2\u0084\u00a2 technology allows users to control up to six EA234WMi displays in a multi-monitor configuration. Smart sensing technology automatically detects your work conditions to determine the proper display brightness with ambient light and human sensors, while a comprehensive input panel, including HDMI, DisplayPort, DVI-D, VGA and 4-port USB hub, connects users to the latest peripherals and future-proofs the investment.\nProduct Type:\nLCD Monitor Technical Information\nNumber of Screens:\n1\nScreen Size:\n23\"\nScreen Mode:\nFull HD\nResponse Time:\n6 ms\nAspect Ratio:\n16:9\nHorizontal Viewing Angle:\n178\u00c2\u00b0\nVertical Viewing Angle:\n178\u00c2\u00b0\nAdjustable Display Angle:\nYes\nAdjustable Display Height:\nYes\nAdjustable Display Pivot:\nYes\nBacklight Technology:\nLED\nHDCP Supported:\nYes\nFeatures:\nIn-plane Switching (IPS) Technology\nSmart Sensing Technology\nAmbient Light Sensor\nEco Mode\nCarbon Footprint Meter\nCable Management\nAuto Brightness Control (ABC)\nAccuColor\nSync on Green Video\nMaximum Resolution:\n1920 x 1080\nStandard Refresh Rate:\n75 Hz\nColor Supported:\n16.7 Million Colors\nContrast Ratio:\n1,000:1\nBrightness:\n250 Nit Audio\nSpeakers:\nYes Interfaces/Ports\nDVI:\nYes\nHDMI:\nYes\nUSB:\nYes\nUSB Standard:\nUSB 2.0\nVGA:\nYes\nDisplayPort:\nYes Built-in Devices\nBuilt-in Devices:\nUSB Hub\nSpeaker Power Description\nOperating Power Consumption:\n27 W\nStandby Power Consumption:\n410 mW Physical Characteristics\nVESA Mount Compatible:\nYes\nVESA Mount Standard:\n100 x 100\nHeight:\n12.7\"\nWidth:\n21.4\"\nDepth:\n2.4\"\nHeight with Stand:\n20.10\"\nWidth with Stand:\n21.40\"\nDepth with Stand:\n8.60\"\nWeight (Approximate):\n8.80 lb\nWeight with Stand (Approximate):\n14.10 lb Shipping Information\nShipping Dimensions :\n10.6\" Height x 18.1\" Width x 23.5\" Depth\nShipping Weight :\n19.4 lb Miscellaneous\nPackage Contents:\n23\" Widescreen LED-Backlit Desktop Monitor w/ IPS LCD Panel\nSetup Sheet\nUser Manual\nPower Cord\n15-pin D-sub Cable\nDVI Cable\nUSB Cable\nAudio Cable\nCertifications & Standards:\nISO 9241-307 Class I\nGreen Compliant:\nYes\nGreen Compliance Certificate/Authority:\nENERGY STAR 6.0\nTCO Certified Edge\nEPEAT Gold\nRoHS Warranty\nLimited Warranty:\n3 Year",
    "main features": "Limited Warranty: 3 Year\nManufacturer/Supplier: NEC Display Solutions\nManufacturer Part Number: EA234WMI-BK\nManufacturer Website Address: http://www.necdisplay.com\nBrand Name: NEC Display\nProduct Line: MultiSync\nProduct Series: EA\nProduct Model: EA234WMi-BK\nProduct Name: 23\" Widescreen LED-Backlit Desktop Monitor w/ IPS LCD Panel\nMarketing Information: The 23\" NEC MultiSync EA234WMi is an LED-backlit desktop monitor ideal for corporate environments. Designed to enhance work performance, this widescreen model features IPS panel technology with wide viewing angles and ergonomic adjustability. The LED backlighting of the EA234WMi allows for a slimmer profile, lighter weight and increased power savings compared to previous generation models. ControlSync\u00e2\u0084\u00a2 technology allows users to control up to six EA234WMi displays in a multi-monitor configuration. Smart sensing technology automatically detects your work conditions to determine the proper display brightness with ambient light and human sensors, while a comprehensive input panel, including HDMI, DisplayPort, DVI-D, VGA and 4-port USB hub, connects users to the latest peripherals and future-proofs the investment.\nProduct Type: LCD Monitor\nNumber of Screens: 1\nScreen Size: 23\"\nScreen Mode: Full HD\nResponse Time: 6 ms\nAspect Ratio: 16:9\nHorizontal Viewing Angle: 178\u00c2\u00b0\nVertical Viewing Angle: 178\u00c2\u00b0\nAdjustable Display Angle: Yes\nAdjustable Display Height: Yes\nAdjustable Display Pivot: Yes\nBacklight Technology: LED\nHDCP Supported: Yes\nFeatures: In-plane Switching (IPS) Technology, Smart Sensing Technology, Ambient Light Sensor, Eco Mode, Carbon Footprint Meter, Cable Management, Auto Brightness Control (ABC), AccuColor, Sync on Green\nMaximum Resolution: 1920 x 1080\nStandard Refresh Rate: 75 Hz\nColor Supported: 16.7 Million Colors\nContrast Ratio: 1,000:1\nBrightness: 250 Nit\nSpeakers: Yes\nDVI: Yes\nHDMI: Yes\nUSB: Yes\nVGA: Yes\nDisplayPort: Yes\nBuilt-in Devices: USB Hub, Speaker\nOperating Power Consumption: 27 W\nStandby Power Consumption: 410 mW\nVESA Mount Compatible: Yes\nVESA Mount Standard: 100 x 100\nHeight: 12.7\"\nWidth: 21.4\"\nDepth: 2.4\"\nHeight with Stand: 20.10\"\nWidth with Stand: 21.40\"\nDepth with Stand: 8.60\"\nWeight (Approximate): 8.80 lb\nWeight with Stand (Approximate): 14.10 lb\nPackage Contents:\n23\" Widescreen LED-Backlit Desktop Monitor w/ IPS LCD Panel , Setup Sheet , User Manual , Power Cord , 15-pin D-sub Cable , DVI Cable , USB Cable , Audio Cable\nCertifications & Standards: ISO 9241-307 Class I\nGreen Compliant: Yes\nGreen Compliance Certificate/Authority: ENERGY STAR 6.0, TCO Certified Edge, EPEAT Gold, RoHS\nGeneral Information\nManufacturer/Supplier:\nNEC Display Solutions\nManufacturer Part Number:\nEA234WMI-BK\nManufacturer Website Address:\nhttp://www.necdisplay.com\nBrand Name:\nNEC Display\nProduct Line:\nMultiSync\nProduct Series:\nEA\nProduct Model:\nEA234WMi-BK\nProduct Name:\n23\" Widescreen LED-Backlit Desktop Monitor w/ IPS LCD Panel\nMarketing Information:\nThe 23\" NEC MultiSync EA234WMi is an LED-backlit desktop monitor ideal for corporate environments. Designed to enhance work performance, this widescreen model features IPS panel technology with wide viewing angles and ergonomic adjustability. The LED backlighting of the EA234WMi allows for a slimmer profile, lighter weight and increased power savings compared to previous generation models. ControlSync\u00e2\u0084\u00a2 technology allows users to control up to six EA234WMi displays in a multi-monitor configuration. Smart sensing technology automatically detects your work conditions to determine the proper display brightness with ambient light and human sensors, while a comprehensive input panel, including HDMI, DisplayPort, DVI-D, VGA and 4-port USB hub, connects users to the latest peripherals and future-proofs the investment.\nProduct Type:\nLCD Monitor\nTechnical Information\nNumber of Screens:\n1\nScreen Size:\n23\"\nScreen Mode:\nFull HD\nResponse Time:\n6 ms\nAspect Ratio:\n16:9\nHorizontal Viewing Angle:\n178\u00c2\u00b0\nVertical Viewing Angle:\n178\u00c2\u00b0\nAdjustable Display Angle:\nYes\nAdjustable Display Height:\nYes\nAdjustable Display Pivot:\nYes\nBacklight Technology:\nLED\nHDCP Supported:\nYes\nFeatures:\nIn-plane Switching (IPS) Technology\nSmart Sensing Technology\nAmbient Light Sensor\nEco Mode\nCarbon Footprint Meter\nCable Management\nAuto Brightness Control (ABC)\nAccuColor\nSync on Green\nVideo\nMaximum Resolution:\n1920 x 1080\nStandard Refresh Rate:\n75 Hz\nColor Supported:\n16.7 Million Colors\nContrast Ratio:\n1,000:1\nBrightness:\n250 Nit\nAudio\nSpeakers:\nYes\nInterfaces/Ports\nDVI:\nYes\nHDMI:\nYes\nUSB:\nYes\nUSB Standard:\nUSB 2.0\nVGA:\nYes\nDisplayPort:\nYes\nBuilt-in Devices\nBuilt-in Devices:\nUSB Hub\nSpeaker\nPower Description\nOperating Power Consumption:\n27 W\nStandby Power Consumption:\n410 mW\nPhysical Characteristics\nVESA Mount Compatible:\nYes\nVESA Mount Standard:\n100 x 100\nHeight:\n12.7\"\nWidth:\n21.4\"\nDepth:\n2.4\"\nHeight with Stand:\n20.10\"\nWidth with Stand:\n21.40\"\nDepth with Stand:\n8.60\"\nWeight (Approximate):\n8.80 lb\nWeight with Stand (Approximate):\n14.10 lb\nShipping Information\nShipping Dimensions :\n10.6\" Height x 18.1\" Width x 23.5\" Depth\nShipping Weight :\n19.4 lb\nMiscellaneous\nPackage Contents:\n23\" Widescreen LED-Backlit Desktop Monitor w/ IPS LCD Panel\nSetup Sheet\nUser Manual\nPower Cord\n15-pin D-sub Cable\nDVI Cable\nUSB Cable\nAudio Cable\nCertifications & Standards:\nISO 9241-307 Class I\nGreen Compliant:\nYes\nGreen Compliance Certificate/Authority:\nENERGY STAR 6.0\nTCO Certified Edge\nEPEAT Gold\nRoHS\nWarranty\nLimited Warranty:\n3 Year",
    "manufacturer part number": "EA234WMI-BK",
    "manufacturer website address": "http://www.necdisplay.com",
    "manufacturersupplier": "NEC Display Solutions",
    "marketing information": "The 23\" NEC MultiSync EA234WMi is an LED-backlit desktop monitor ideal for corporate environments. Designed to enhance work performance, this widescreen model features IPS panel technology with wide viewing angles and ergonomic adjustability. The LED backlighting of the EA234WMi allows for a slimmer profile, lighter weight and increased power savings compared to previous generation models. ControlSync\u00e2\u0084\u00a2 technology allows users to control up to six EA234WMi displays in a multi-monitor configuration. Smart sensing technology automatically detects your work conditions to determine the proper display brightness with ambient light and human sensors, while a comprehensive input panel, including HDMI, DisplayPort, DVI-D, VGA and 4-port USB hub, connects users to the latest peripherals and future-proofs the investment.",
    "package contents": "23\" Widescreen LED-Backlit Desktop Monitor w/ IPS LCD Panel , Setup Sheet , User Manual , Power Cord , 15-pin D-sub Cable , DVI Cable , USB Cable , Audio Cable",
    "product line": "MultiSync",
    "product model": "EA234WMi-BK",
    "product name": "23\" Widescreen LED-Backlit Desktop Monitor w/ IPS LCD Panel",
    "product series": "EA",
    "product type": "LCD Monitor"
}