{
    "<page title>": "Viewsonic VA2251M LED 22\" LED LCD Monitor 16 9 5 MS 1920x1080 1000 1 VGA DVI 766907613018 | eBay",
    "brand name": "Viewsonic",
    "certifications  standards": "CB , CE , UL/c UL , FCC-B , ULAR , GOST-R/Hygienic , UkrSEPRO + DoC , CCC , CEL Level 1 , BSMI , PSB , C-tick , SASO , e-standby , KC",
    "main features": "Manufacturer/Supplier: Viewsonic Corporation\nManufacturer Part Number: VA2251m-LED\nManufacturer Website Address: www.viewsonic.com\nBrand Name: Viewsonic\nProduct Model: VA2251m-LED\nProduct Name: 22\" Full HD 1080p LED Monitor\nMarketing Information: ViewSonic's new 22-inch eco-friendly monitors, the VA2251m-LED, are cost effective and produce a Full HD 1080p viewing experience. Featuring a widescreen superlative Full HD 1080p 1920 x 1080 resolution, the VA2251m-LED deliver immaculate images for work and home environments. An incorporated LED backlight as well as a power-saving ECO Mode produces higher levels of brightness and refine image details even in low light conditions. Reducing power consumption with three different brightness throughputs helps to save on energy and accommodate different environments. Built-in sRGB color correction technology and dynamic contrast ratios also manage pixel quality to the finest detail and produces a most comfortable viewing experience.\nProduct Type: LCD Monitor\nNumber of Screens: 1\nScreen Size: 22\"\nScreen Mode: Full HD\nResponse Time: 5 ms\nAspect Ratio: 16:9\nHorizontal Viewing Angle: 170\u00c2\u00b0\nVertical Viewing Angle: 160\u00c2\u00b0\nMount Type: Wall Mountable\nBacklight Technology: LED\nFeatures: Security Lock\nMaximum Resolution: 1920 x 1080\nStandard Refresh Rate: 75 Hz\nContrast Ratio: 1,000:1\nBrightness: 250 Nit\nSpeakers: Yes\nDVI: Yes\nVGA: Yes\nInput Voltage: 110 V AC, 220 V AC\nOperating Power Consumption: 30 W\nVESA Mount Compatible: Yes\nVESA Mount Standard: 100 x 100\nHeight: 12.2\"\nWidth: 20.0\"\nDepth: 2.4\"\nHeight with Stand: 14.61\"\nWidth with Stand: 20.13\"\nDepth with Stand: 6.45\"\nWeight (Approximate): 7.12 lb\nWeight with Stand (Approximate): 7.80 lb\nCertifications & Standards:\nCB , CE , UL/c UL , FCC-B , ULAR , GOST-R/Hygienic , UkrSEPRO + DoC , CCC , CEL Level 1 , BSMI , PSB , C-tick , SASO , e-standby , KC\nPlatform Supported: PC, Mac\nGreen Compliant: Yes\nGreen Compliance Certificate/Authority: REACH, WEEE, EPEAT Silver, Energy Star, ErP General Information\nManufacturer/Supplier:\nViewsonic Corporation\nManufacturer Part Number:\nVA2251m-LED\nManufacturer Website Address:\nwww.viewsonic.com\nBrand Name:\nViewsonic\nProduct Model:\nVA2251m-LED\nProduct Name:\n22\" Full HD 1080p LED Monitor\nMarketing Information:\nViewSonic's new 22-inch eco-friendly monitors, the VA2251m-LED, are cost effective and produce a Full HD 1080p viewing experience. Featuring a widescreen superlative Full HD 1080p 1920 x 1080 resolution, the VA2251m-LED deliver immaculate images for work and home environments. An incorporated LED backlight as well as a power-saving ECO Mode produces higher levels of brightness and refine image details even in low light conditions. Reducing power consumption with three different brightness throughputs helps to save on energy and accommodate different environments. Built-in sRGB color correction technology and dynamic contrast ratios also manage pixel quality to the finest detail and produces a most comfortable viewing experience.\nProduct Type:\nLCD Monitor Technical Information\nNumber of Screens:\n1\nScreen Size:\n22\"\nScreen Mode:\nFull HD\nScreen Surface:\nAnti-glare\nResponse Time:\n5 ms\nAspect Ratio:\n16:9\nHorizontal Viewing Angle:\n170\u00c2\u00b0\nVertical Viewing Angle:\n160\u00c2\u00b0\nMount Type:\nWall Mountable\nBacklight Technology:\nLED\nFeatures:\nSecurity Lock Video\nMaximum Resolution:\n1920 x 1080\nStandard Refresh Rate:\n75 Hz\nContrast Ratio:\n1,000:1\nBrightness:\n250 Nit Audio\nNumber of Speakers:\n2\nSpeakers:\nYes Interfaces/Ports\nDVI:\nYes\nVGA:\nYes Power Description\nInput Voltage:\n110 V AC\n220 V AC\nOperating Power Consumption:\n30 W Physical Characteristics\nVESA Mount Compatible:\nYes\nVESA Mount Standard:\n100 x 100\nHeight:\n12.2\"\nWidth:\n20.0\"\nDepth:\n2.4\"\nHeight with Stand:\n14.61\"\nWidth with Stand:\n20.13\"\nDepth with Stand:\n6.45\"\nWeight (Approximate):\n7.12 lb\nWeight with Stand (Approximate):\n7.80 lb Shipping Information\nShipping Dimensions :\n5.0\" Height x 16.5\" Width x 22.4\" Depth\nCase Pack Qty :\n1\nShipping Weight :\n10.1 lb\nMiscellaneous\nCertifications & Standards:\nCB\nCE\nUL/c UL\nFCC-B\nULAR\nGOST-R/Hygienic\nUkrSEPRO + DoC\nCCC\nCEL Level 1\nBSMI\nPSB\nC-tick\nSASO\ne-standby\nKC\nPlatform Supported:\nPC\nMac\nGreen Compliant:\nYes\nGreen Compliance Certificate/Authority:\nREACH\nWEEE\nEPEAT Silver\nEnergy Star\nErP",
    "manufacturer part number": "VA2251m-LED",
    "manufacturer website address": "www.viewsonic.com",
    "manufacturersupplier": "Viewsonic Corporation",
    "marketing information": "ViewSonic's new 22-inch eco-friendly monitors, the VA2251m-LED, are cost effective and produce a Full HD 1080p viewing experience. Featuring a widescreen superlative Full HD 1080p 1920 x 1080 resolution, the VA2251m-LED deliver immaculate images for work and home environments. An incorporated LED backlight as well as a power-saving ECO Mode produces higher levels of brightness and refine image details even in low light conditions. Reducing power consumption with three different brightness throughputs helps to save on energy and accommodate different environments. Built-in sRGB color correction technology and dynamic contrast ratios also manage pixel quality to the finest detail and produces a most comfortable viewing experience.",
    "product model": "VA2251m-LED",
    "product name": "22\" Full HD 1080p LED Monitor",
    "product type": "LCD Monitor"
}